{
  "train": [
    {
      "name": "Cheese Brush",
      "price": 5000,
      "": 0
    },
    {
      "name": "Verdant Brush",
      "price": 26548,
      "": -548.5565188968721
    },
    {
      "name": "Azure Brush",
      "price": 66024,
      "": 1975.8158190768008
    },
    {
      "name": "Burble Brush",
      "price": 151938,
      "": 8061.928254873259
    },
    {
      "name": "Crimson Brush",
      "price": 319665,
      "": 10334.464869442105
    },
    {
      "name": "Rainbow Brush",
      "price": 603802,
      "": 16197.060614978895
    },
    {
      "name": "Holy Brush",
      "price": 1146585,
      "": -96585.4487342604
    },
    {
      "name": "Cheese Shears",
      "price": 5000,
      "": 0
    },
    {
      "name": "Verdant Shears",
      "price": 26548,
      "": -548.5565188968721
    },
    {
      "name": "Azure Shears",
      "price": 66024,
      "": 1975.8158190768008
    },
    {
      "name": "Burble Shears",
      "price": 151938,
      "": 3061.928254873259
    },
    {
      "name": "Crimson Shears",
      "price": 319665,
      "": 10334.464869442105
    },
    {
      "name": "Rainbow Shears",
      "price": 603802,
      "": 16197.060614978895
    },
    {
      "name": "Holy Shears",
      "price": 1146585,
      "": 3414.551265739603
    },
    {
      "name": "Cheese Hatchet",
      "price": 5000,
      "": 0
    },
    {
      "name": "Verdant Hatchet",
      "price": 26548,
      "": -548.5565188968721
    },
    {
      "name": "Azure Hatchet",
      "price": 66024,
      "": 1975.8158190768008
    },
    {
      "name": "Burble Hatchet",
      "price": 151938,
      "": 8061.928254873259
    },
    {
      "name": "Crimson Hatchet",
      "price": 319665,
      "": 334.4648694421048
    },
    {
      "name": "Rainbow Hatchet",
      "price": 603802,
      "": 16197.060614978895
    },
    {
      "name": "Holy Hatchet",
      "price": 1146585,
      "": -46585.4487342604
    },
    {
      "name": "Cheese Hammer",
      "price": 5000,
      "": 0
    },
    {
      "name": "Verdant Hammer",
      "price": 26563,
      "": -563.3207052072394
    },
    {
      "name": "Azure Hammer",
      "price": 66054,
      "": 1945.359975439511
    },
    {
      "name": "Burble Hammer",
      "price": 151997,
      "": 8002.005600641773
    },
    {
      "name": "Crimson Hammer",
      "price": 319780,
      "": 10219.559763202677
    },
    {
      "name": "Rainbow Hammer",
      "price": 604025,
      "": -4025.264221477206
    },
    {
      "name": "Holy Hammer",
      "price": 1147018,
      "": -47018.933103227755
    },
    {
      "name": "Cheese Chisel",
      "price": 5000,
      "": 0
    },
    {
      "name": "Verdant Chisel",
      "price": 26563,
      "": -563.3207052072394
    },
    {
      "name": "Azure Chisel",
      "price": 66054,
      "": 1945.359975439511
    },
    {
      "name": "Burble Chisel",
      "price": 151997,
      "": 8002.005600641773
    },
    {
      "name": "Crimson Chisel",
      "price": 319780,
      "": 10219.559763202677
    },
    {
      "name": "Rainbow Chisel",
      "price": 604025,
      "": 15974.735778522794
    },
    {
      "name": "Holy Chisel",
      "price": 1147018,
      "": -47018.933103227755
    },
    {
      "name": "Cheese Spatula",
      "price": 5000,
      "": 0
    },
    {
      "name": "Verdant Spatula",
      "price": 28247,
      "": -247.00029704397093
    },
    {
      "name": "Azure Spatula",
      "price": 68534,
      "": 3465.100791766061
    },
    {
      "name": "Burble Spatula",
      "price": 156216,
      "": 3783.7545802336244
    },
    {
      "name": "Crimson Spatula",
      "price": 328723,
      "": 1276.1434366719914
    },
    {
      "name": "Rainbow Spatula",
      "price": 621912,
      "": -1912.0968745384598
    },
    {
      "name": "Holy Spatula",
      "price": 1193582,
      "": -43582.63106241124
    },
    {
      "name": "Cheese Needle",
      "price": 5000,
      "": 0
    },
    {
      "name": "Verdant Needle",
      "price": 28247,
      "": -247.00029704397093
    },
    {
      "name": "Azure Needle",
      "price": 68534,
      "": 3465.100791766061
    },
    {
      "name": "Burble Needle",
      "price": 156216,
      "": 8783.754580233624
    },
    {
      "name": "Crimson Needle",
      "price": 328723,
      "": 11276.143436671991
    },
    {
      "name": "Rainbow Needle",
      "price": 621912,
      "": -21912.09687453846
    },
    {
      "name": "Holy Needle",
      "price": 1193582,
      "": -93582.63106241124
    },
    {
      "name": "Cheese Pot",
      "price": 5000,
      "": 0
    },
    {
      "name": "Verdant Pot",
      "price": 28247,
      "": -247.00029704397093
    },
    {
      "name": "Azure Pot",
      "price": 68534,
      "": 1465.1007917660609
    },
    {
      "name": "Burble Pot",
      "price": 156216,
      "": 3783.7545802336244
    },
    {
      "name": "Crimson Pot",
      "price": 328723,
      "": 11276.143436671991
    },
    {
      "name": "Rainbow Pot",
      "price": 621912,
      "": -1912.0968745384598
    },
    {
      "name": "Holy Pot",
      "price": 1193582,
      "": 6417.3689375887625
    },
    {
      "name": "Cheese Alembic",
      "price": 5000,
      "": 0
    },
    {
      "name": "Verdant Alembic",
      "price": 28261,
      "": -761.9622290951193
    },
    {
      "name": "Azure Alembic",
      "price": 68565,
      "": 1434.2271539049398
    },
    {
      "name": "Burble Alembic",
      "price": 156277,
      "": 8722.977974131878
    },
    {
      "name": "Crimson Alembic",
      "price": 328840,
      "": 11159.522719699831
    },
    {
      "name": "Rainbow Alembic",
      "price": 622137,
      "": 17862.074137975927
    },
    {
      "name": "Holy Alembic",
      "price": 1194023,
      "": 5976.630470291013
    },
    {
      "name": "Cheese Enhancer",
      "price": 5000,
      "": 0
    },
    {
      "name": "Verdant Enhancer",
      "price": 28261,
      "": 238.03777090488074
    },
    {
      "name": "Azure Enhancer",
      "price": 68565,
      "": 3434.2271539049398
    },
    {
      "name": "Burble Enhancer",
      "price": 156277,
      "": -1277.022025868122
    },
    {
      "name": "Crimson Enhancer",
      "price": 328840,
      "": 1159.5227196998312
    },
    {
      "name": "Rainbow Enhancer",
      "price": 622137,
      "": 17862.074137975927
    },
    {
      "name": "Holy Enhancer",
      "price": 1194023,
      "": 5976.630470291013
    },
    {
      "name": "Cheese Bulwark",
      "price": 14272,
      "": -772.8833879618815
    },
    {
      "name": "Verdant Bulwark",
      "price": 51572,
      "": -25572.781861061347
    },
    {
      "name": "Azure Bulwark",
      "price": 119040,
      "": -31040.754749685235
    },
    {
      "name": "Burble Bulwark",
      "price": 266510,
      "": -76510.59139787348
    },
    {
      "name": "Crimson Bulwark",
      "price": 557231,
      "": -137231.43083754147
    },
    {
      "name": "Rainbow Bulwark",
      "price": 1050634,
      "": -150634.27031530906
    },
    {
      "name": "Holy Bulwark",
      "price": 2013676,
      "": -113676.76957391668
    },
    {
      "name": "Cheese Sword",
      "price": 5000,
      "": 0
    },
    {
      "name": "Verdant Sword",
      "price": 34199,
      "": -199.2738896570154
    },
    {
      "name": "Azure Sword",
      "price": 85326,
      "": 2673.8346089211846
    },
    {
      "name": "Burble Sword",
      "price": 196860,
      "": -1860.8597297303204
    },
    {
      "name": "Crimson Sword",
      "price": 416537,
      "": 3462.032829577569
    },
    {
      "name": "Rainbow Sword",
      "price": 789585,
      "": 30414.224269167404
    },
    {
      "name": "Holy Sword",
      "price": 1517360,
      "": -17360.211617941968
    },
    {
      "name": "Cheese Spear",
      "price": 5000,
      "": 0
    },
    {
      "name": "Verdant Spear",
      "price": 30846,
      "": 153.41851333648447
    },
    {
      "name": "Azure Spear",
      "price": 80395,
      "": 3604.102854669094
    },
    {
      "name": "Burble Spear",
      "price": 188483,
      "": 6516.139887915488
    },
    {
      "name": "Crimson Spear",
      "price": 398765,
      "": 11234.80397748889
    },
    {
      "name": "Rainbow Spear",
      "price": 754032,
      "": 25967.286178288865
    },
    {
      "name": "Holy Spear",
      "price": 1424662,
      "": 25337.2596450157
    },
    {
      "name": "Cheese Mace",
      "price": 5000,
      "": 0
    },
    {
      "name": "Verdant Mace",
      "price": 30861,
      "": 138.55594757828658
    },
    {
      "name": "Azure Mace",
      "price": 80426,
      "": 3573.439181908514
    },
    {
      "name": "Burble Mace",
      "price": 188544,
      "": 6455.792527334095
    },
    {
      "name": "Crimson Mace",
      "price": 398880,
      "": 11119.045847728848
    },
    {
      "name": "Rainbow Mace",
      "price": 754256,
      "": 25743.219585763174
    },
    {
      "name": "Holy Mace",
      "price": 1425099,
      "": 24900.17092317622
    },
    {
      "name": "Cheese Buckler",
      "price": 7535,
      "": -3335.5328405164364
    },
    {
      "name": "Verdant Buckler",
      "price": 26907,
      "": 1092.5336892722225
    },
    {
      "name": "Azure Buckler",
      "price": 61780,
      "": 219.94756206819147
    },
    {
      "name": "Burble Buckler",
      "price": 137542,
      "": -7542.60774015385
    },
    {
      "name": "Crimson Buckler",
      "price": 286480,
      "": -1480.2364639735315
    },
    {
      "name": "Rainbow Buckler",
      "price": 539767,
      "": -159767.66463753418
    },
    {
      "name": "Holy Buckler",
      "price": 1033443,
      "": -173443.47565215803
    },
    {
      "name": "Cheese Helmet",
      "price": 6413,
      "": 186.92022070805342
    },
    {
      "name": "Verdant Helmet",
      "price": 22797,
      "": 1202.1602198844776
    },
    {
      "name": "Azure Helmet",
      "price": 52239,
      "": 3760.79858247636
    },
    {
      "name": "Burble Helmet",
      "price": 116053,
      "": -1053.0628421946603
    },
    {
      "name": "Crimson Helmet",
      "price": 241364,
      "": 3635.134964597848
    },
    {
      "name": "Rainbow Helmet",
      "price": 454642,
      "": 15357.727199200424
    },
    {
      "name": "Holy Helmet",
      "price": 870108,
      "": -30108.451162362006
    },
    {
      "name": "Cheese Plate Body",
      "price": 9788,
      "": 11.612243296138331
    },
    {
      "name": "Verdant Plate Body",
      "price": 35149,
      "": 850.4581758037675
    },
    {
      "name": "Azure Plate Body",
      "price": 80908,
      "": 1091.1326864778239
    },
    {
      "name": "Burble Plate Body",
      "price": 180614,
      "": 9385.495960126835
    },
    {
      "name": "Crimson Plate Body",
      "price": 376889,
      "": 13110.787563044752
    },
    {
      "name": "Rainbow Plate Body",
      "price": 710363,
      "": 29636.053705623723
    },
    {
      "name": "Holy Plate Body",
      "price": 1360788,
      "": -10788.639449574985
    },
    {
      "name": "Cheese Plate Legs",
      "price": 8663,
      "": -263.26762231320754
    },
    {
      "name": "Verdant Plate Legs",
      "price": 31032,
      "": -32.25651972081687
    },
    {
      "name": "Azure Plate Legs",
      "price": 71352,
      "": 2647.7964476004563
    },
    {
      "name": "Burble Plate Legs",
      "price": 159093,
      "": 906.198385953583
    },
    {
      "name": "Crimson Plate Legs",
      "price": 331713,
      "": 8286.01694655756
    },
    {
      "name": "Rainbow Plate Legs",
      "price": 625122,
      "": 14877.526510194875
    },
    {
      "name": "Holy Plate Legs",
      "price": 1197226,
      "": 2773.32262842427
    },
    {
      "name": "Cheese Gauntlets",
      "price": 5277,
      "": -77.72034762570911
    },
    {
      "name": "Verdant Gauntlets",
      "price": 18651,
      "": 848.8220287103286
    },
    {
      "name": "Azure Gauntlets",
      "price": 42621,
      "": 3378.0529762681326
    },
    {
      "name": "Burble Gauntlets",
      "price": 94413,
      "": 1586.8280253717094
    },
    {
      "name": "Crimson Gauntlets",
      "price": 195961,
      "": 9038.85323774087
    },
    {
      "name": "Rainbow Gauntlets",
      "price": 368958,
      "": 11041.146718147094
    },
    {
      "name": "Holy Gauntlets",
      "price": 705685,
      "": -5685.125903656473
    },
    {
      "name": "Cheese Boots",
      "price": 5277,
      "": -277.7203476257091
    },
    {
      "name": "Verdant Boots",
      "price": 18646,
      "": 853.5516919227593
    },
    {
      "name": "Azure Boots",
      "price": 42609,
      "": 2390.4940496345953
    },
    {
      "name": "Burble Boots",
      "price": 94386,
      "": 1613.7364077473321
    },
    {
      "name": "Crimson Boots",
      "price": 195907,
      "": 9092.727891228045
    },
    {
      "name": "Rainbow Boots",
      "price": 368852,
      "": 11147.643305060803
    },
    {
      "name": "Holy Boots",
      "price": 705475,
      "": -5475.326505769044
    },
    {
      "name": "Rough Hood",
      "price": 9852,
      "": -652.8552894960285
    },
    {
      "name": "Reptile Hood",
      "price": 49071,
      "": 928.2732136353297
    },
    {
      "name": "Gobo Hood",
      "price": 102927,
      "": -12927.83892467132
    },
    {
      "name": "Beast Hood",
      "price": 211434,
      "": -1434.9513030695962
    },
    {
      "name": "Umbral Hood",
      "price": 574304,
      "": -174304.80390183
    },
    {
      "name": "Cotton Hat",
      "price": 6050,
      "": -450.9981466388854
    },
    {
      "name": "Linen Hat",
      "price": 15398,
      "": 1101.86505037003
    },
    {
      "name": "Bamboo Hat",
      "price": 35037,
      "": 962.4671977776525
    },
    {
      "name": "Silk Hat",
      "price": 219581,
      "": 10418.211962236528
    },
    {
      "name": "Radiant Hat",
      "price": 647626,
      "": -177626.33451407484
    },
    {
      "name": "Rough Tunic",
      "price": 15300,
      "": -300.1367464053583
    },
    {
      "name": "Reptile Tunic",
      "price": 76831,
      "": 3168.5264256117953
    },
    {
      "name": "Gobo Tunic",
      "price": 160259,
      "": -259.8076050270174
    },
    {
      "name": "Beast Tunic",
      "price": 327688,
      "": 2311.892091745918
    },
    {
      "name": "Umbral Tunic",
      "price": 896412,
      "": 3587.8104213608894
    },
    {
      "name": "Cotton Robe Top",
      "price": 9217,
      "": -1017.1653178339293
    },
    {
      "name": "Linen Robe Top",
      "price": 22953,
      "": 1046.2733643872998
    },
    {
      "name": "Bamboo Robe Top",
      "price": 51635,
      "": 2364.68219089137
    },
    {
      "name": "Silk Robe Top",
      "price": 340723,
      "": -10723.04668376426
    },
    {
      "name": "Radiant Robe Top",
      "price": 1013726,
      "": -113726.63855823106
    },
    {
      "name": "Rough Chaps",
      "price": 13481,
      "": -481.62040976508797
    },
    {
      "name": "Reptile Chaps",
      "price": 67567,
      "": 2432.170789565731
    },
    {
      "name": "Gobo Chaps",
      "price": 141120,
      "": -6120.179200700863
    },
    {
      "name": "Beast Chaps",
      "price": 288862,
      "": 1137.511837590544
    },
    {
      "name": "Umbral Chaps",
      "price": 788872,
      "": -48872.51302999444
    },
    {
      "name": "Cotton Robe Bottoms",
      "price": 8159,
      "": -359.0204097650885
    },
    {
      "name": "Linen Robe Bottoms",
      "price": 20424,
      "": 2575.1993609943056
    },
    {
      "name": "Bamboo Robe Bottoms",
      "price": 46073,
      "": 5926.249370727695
    },
    {
      "name": "Silk Robe Bottoms",
      "price": 300268,
      "": 9731.940409019066
    },
    {
      "name": "Radiant Robe Bottoms",
      "price": 891522,
      "": -31522.6558871374
    },
    {
      "name": "Rough Bracers",
      "price": 8034,
      "": 565.3469414422225
    },
    {
      "name": "Reptile Bracers",
      "price": 39809,
      "": -809.3106670992565
    },
    {
      "name": "Gobo Bracers",
      "price": 83791,
      "": 2208.180157402501
    },
    {
      "name": "Beast Bracers",
      "price": 172619,
      "": -2619.23289248714
    },
    {
      "name": "Umbral Bracers",
      "price": 466789,
      "": -6789.372709456831
    },
    {
      "name": "Cotton Gloves",
      "price": 4993,
      "": -193.16734427206302
    },
    {
      "name": "Linen Gloves",
      "price": 12870,
      "": -1370.4371977115024
    },
    {
      "name": "Bamboo Gloves",
      "price": 29479,
      "": 1520.4250553616985
    },
    {
      "name": "Silk Gloves",
      "price": 179136,
      "": 5863.297719757742
    },
    {
      "name": "Radiant Gloves",
      "price": 525446,
      "": -135446.5971992528
    },
    {
      "name": "Rough Boots",
      "price": 8029,
      "": -29.54075578897573
    },
    {
      "name": "Reptile Boots",
      "price": 39783,
      "": 40216.90577823291
    },
    {
      "name": "Gobo Boots",
      "price": 83714,
      "": 36285.402815078734
    },
    {
      "name": "Beast Boots",
      "price": 172417,
      "": -2417.6996619476413
    },
    {
      "name": "Umbral Boots",
      "price": 466328,
      "": -16328.318328418827
    },
    {
      "name": "Cotton Boots",
      "price": 4988,
      "": -88.05504150326124
    },
    {
      "name": "Linen Boots",
      "price": 12844,
      "": 155.77924762066505
    },
    {
      "name": "Bamboo Boots",
      "price": 29402,
      "": -902.352286962072
    },
    {
      "name": "Silk Boots",
      "price": 178935,
      "": 6064.83095029727
    },
    {
      "name": "Radiant Boots",
      "price": 524985,
      "": -4985.542818214744
    },
    {
      "name": "Wooden Crossbow",
      "price": 5000,
      "": 0
    },
    {
      "name": "Birch Crossbow",
      "price": 30284,
      "": -284.06259379152834
    },
    {
      "name": "Cedar Crossbow",
      "price": 86291,
      "": -6291.344725875606
    },
    {
      "name": "Purpleheart Crossbow",
      "price": 197811,
      "": 7188.4282444820565
    },
    {
      "name": "Ginkgo Crossbow",
      "price": 413795,
      "": -33795.63639448624
    },
    {
      "name": "Redwood Crossbow",
      "price": 776199,
      "": 3800.064733632258
    },
    {
      "name": "Arcane Crossbow",
      "price": 1386556,
      "": -36556.61936291214
    },
    {
      "name": "Wooden Water Staff",
      "price": 5000,
      "": 0
    },
    {
      "name": "Birch Water Staff",
      "price": 30284,
      "": -784.0625937915283
    },
    {
      "name": "Cedar Water Staff",
      "price": 86291,
      "": 3708.655274124394
    },
    {
      "name": "Purpleheart Water Staff",
      "price": 197811,
      "": 7188.4282444820565
    },
    {
      "name": "Ginkgo Water Staff",
      "price": 413795,
      "": 6204.363605513761
    },
    {
      "name": "Redwood Water Staff",
      "price": 776199,
      "": -16199.935266367742
    },
    {
      "name": "Arcane Water Staff",
      "price": 1386556,
      "": 13443.38063708786
    },
    {
      "name": "Wooden Nature Staff",
      "price": 5000,
      "": 0
    },
    {
      "name": "Birch Nature Staff",
      "price": 30303,
      "": -803.459037683926
    },
    {
      "name": "Cedar Nature Staff",
      "price": 86334,
      "": 1665.9640791588754
    },
    {
      "name": "Purpleheart Nature Staff",
      "price": 197897,
      "": 7102.017438935902
    },
    {
      "name": "Ginkgo Nature Staff",
      "price": 413963,
      "": 6036.4274468766525
    },
    {
      "name": "Redwood Nature Staff",
      "price": 776527,
      "": 3472.964749717503
    },
    {
      "name": "Arcane Nature Staff",
      "price": 1387196,
      "": -37196.343416208634
    },
    {
      "name": "Wooden Fire Staff",
      "price": 5000,
      "": 0
    },
    {
      "name": "Birch Fire Staff",
      "price": 30325,
      "": -1325.8275352175733
    },
    {
      "name": "Cedar Fire Staff",
      "price": 86380,
      "": 1619.8108273742982
    },
    {
      "name": "Purpleheart Fire Staff",
      "price": 197988,
      "": 7011.17389249921
    },
    {
      "name": "Ginkgo Fire Staff",
      "price": 414137,
      "": -4137.857892544998
    },
    {
      "name": "Redwood Fire Staff",
      "price": 776864,
      "": -36864.45953549328
    },
    {
      "name": "Arcane Fire Staff",
      "price": 1387854,
      "": -37854.71952970885
    },
    {
      "name": "Wooden Bow",
      "price": 5000,
      "": 0
    },
    {
      "name": "Birch Bow",
      "price": 37976,
      "": 23.651865945626923
    },
    {
      "name": "Cedar Bow",
      "price": 111945,
      "": 8054.233059459526
    },
    {
      "name": "Purpleheart Bow",
      "price": 259385,
      "": -9385.478901237366
    },
    {
      "name": "Ginkgo Bow",
      "price": 545161,
      "": 14838.066255892161
    },
    {
      "name": "Redwood Bow",
      "price": 1024333,
      "": -24333.47021015524
    },
    {
      "name": "Arcane Bow",
      "price": 1830739,
      "": -180739.88213804807
    },
    {
      "name": "Wooden Shield",
      "price": 5787,
      "": -887.1825188099474
    },
    {
      "name": "Birch Shield",
      "price": 22532,
      "": -2032.7606005295274
    },
    {
      "name": "Cedar Shield",
      "price": 61153,
      "": -7153.743364596674
    },
    {
      "name": "Purpleheart Shield",
      "price": 137899,
      "": 2100.5404997711885
    },
    {
      "name": "Ginkgo Shield",
      "price": 286308,
      "": -76308.03717137419
    },
    {
      "name": "Redwood Shield",
      "price": 535706,
      "": -175706.46999726596
    },
    {
      "name": "Arcane Shield",
      "price": 956433,
      "": -276433.10995874985
    }
  ],
  "time": 1782338260.498
}