{
  "train": [
    {
      "name": "Cheese Brush",
      "price": 5000,
      "": 0
    },
    {
      "name": "Verdant Brush",
      "price": 26454,
      "": -954.1562041847283
    },
    {
      "name": "Azure Brush",
      "price": 65909,
      "": 2090.3377414952556
    },
    {
      "name": "Burble Brush",
      "price": 148786,
      "": -3786.7759146566386
    },
    {
      "name": "Crimson Brush",
      "price": 312832,
      "": 17167.839472643507
    },
    {
      "name": "Rainbow Brush",
      "price": 594394,
      "": -34394.60303320701
    },
    {
      "name": "Holy Brush",
      "price": 1161967,
      "": -61967.66152893356
    },
    {
      "name": "Cheese Shears",
      "price": 5000,
      "": 0
    },
    {
      "name": "Verdant Shears",
      "price": 26454,
      "": 45.84379581527173
    },
    {
      "name": "Azure Shears",
      "price": 65909,
      "": 4090.3377414952556
    },
    {
      "name": "Burble Shears",
      "price": 148786,
      "": 1213.2240853433614
    },
    {
      "name": "Crimson Shears",
      "price": 312832,
      "": 7167.839472643507
    },
    {
      "name": "Rainbow Shears",
      "price": 594394,
      "": 25605.396966792992
    },
    {
      "name": "Holy Shears",
      "price": 1161967,
      "": -11967.66152893356
    },
    {
      "name": "Cheese Hatchet",
      "price": 5000,
      "": 0
    },
    {
      "name": "Verdant Hatchet",
      "price": 26454,
      "": 45.84379581527173
    },
    {
      "name": "Azure Hatchet",
      "price": 65909,
      "": 90.33774149525561
    },
    {
      "name": "Burble Hatchet",
      "price": 148786,
      "": 1213.2240853433614
    },
    {
      "name": "Crimson Hatchet",
      "price": 312832,
      "": 17167.839472643507
    },
    {
      "name": "Rainbow Hatchet",
      "price": 594394,
      "": 5605.396966792992
    },
    {
      "name": "Holy Hatchet",
      "price": 1161967,
      "": -11967.66152893356
    },
    {
      "name": "Cheese Hammer",
      "price": 5000,
      "": 0
    },
    {
      "name": "Verdant Hammer",
      "price": 26469,
      "": 30.26259324703642
    },
    {
      "name": "Azure Hammer",
      "price": 65941,
      "": 2058.1965412202408
    },
    {
      "name": "Burble Hammer",
      "price": 148850,
      "": 6149.98544865998
    },
    {
      "name": "Crimson Hammer",
      "price": 312953,
      "": 17046.575780977437
    },
    {
      "name": "Rainbow Hammer",
      "price": 594629,
      "": 5370.7691830495605
    },
    {
      "name": "Holy Hammer",
      "price": 1162425,
      "": -62425.13393012551
    },
    {
      "name": "Cheese Chisel",
      "price": 5000,
      "": 0
    },
    {
      "name": "Verdant Chisel",
      "price": 26469,
      "": 30.26259324703642
    },
    {
      "name": "Azure Chisel",
      "price": 65941,
      "": 4058.1965412202408
    },
    {
      "name": "Burble Chisel",
      "price": 148850,
      "": 1149.9854486599797
    },
    {
      "name": "Crimson Chisel",
      "price": 312953,
      "": 7046.575780977437
    },
    {
      "name": "Rainbow Chisel",
      "price": 594629,
      "": 25370.76918304956
    },
    {
      "name": "Holy Chisel",
      "price": 1162425,
      "": -62425.13393012551
    },
    {
      "name": "Cheese Spatula",
      "price": 5000,
      "": 0
    },
    {
      "name": "Verdant Spatula",
      "price": 28370,
      "": -370.66597818153605
    },
    {
      "name": "Azure Spatula",
      "price": 68784,
      "": 3215.8557248937286
    },
    {
      "name": "Burble Spatula",
      "price": 152887,
      "": 2112.77524457837
    },
    {
      "name": "Crimson Spatula",
      "price": 317235,
      "": 12764.960474854975
    },
    {
      "name": "Rainbow Spatula",
      "price": 602911,
      "": -2911.8481638892554
    },
    {
      "name": "Holy Spatula",
      "price": 1198732,
      "": -48732.869644411374
    },
    {
      "name": "Cheese Needle",
      "price": 5000,
      "": 0
    },
    {
      "name": "Verdant Needle",
      "price": 28370,
      "": 129.33402181846395
    },
    {
      "name": "Azure Needle",
      "price": 68784,
      "": 1215.8557248937286
    },
    {
      "name": "Burble Needle",
      "price": 152887,
      "": 2112.77524457837
    },
    {
      "name": "Crimson Needle",
      "price": 317235,
      "": 12764.960474854975
    },
    {
      "name": "Rainbow Needle",
      "price": 602911,
      "": 17088.151836110745
    },
    {
      "name": "Holy Needle",
      "price": 1198732,
      "": -48732.869644411374
    },
    {
      "name": "Cheese Pot",
      "price": 5000,
      "": 0
    },
    {
      "name": "Verdant Pot",
      "price": 28370,
      "": -870.665978181536
    },
    {
      "name": "Azure Pot",
      "price": 68784,
      "": 1215.8557248937286
    },
    {
      "name": "Burble Pot",
      "price": 152887,
      "": 2112.77524457837
    },
    {
      "name": "Crimson Pot",
      "price": 317235,
      "": 12764.960474854975
    },
    {
      "name": "Rainbow Pot",
      "price": 602911,
      "": 17088.151836110745
    },
    {
      "name": "Holy Pot",
      "price": 1198732,
      "": 1267.1303555886261
    },
    {
      "name": "Cheese Alembic",
      "price": 5000,
      "": 0
    },
    {
      "name": "Verdant Alembic",
      "price": 28386,
      "": 113.54413071302406
    },
    {
      "name": "Azure Alembic",
      "price": 68816,
      "": 1183.2736106193624
    },
    {
      "name": "Burble Alembic",
      "price": 152951,
      "": 2048.635400283907
    },
    {
      "name": "Crimson Alembic",
      "price": 317358,
      "": 12641.886234487232
    },
    {
      "name": "Rainbow Alembic",
      "price": 603150,
      "": 16849.82598964544
    },
    {
      "name": "Holy Alembic",
      "price": 1199197,
      "": -49197.99756912142
    },
    {
      "name": "Cheese Enhancer",
      "price": 5000,
      "": 0
    },
    {
      "name": "Verdant Enhancer",
      "price": 28386,
      "": 113.54413071302406
    },
    {
      "name": "Azure Enhancer",
      "price": 68816,
      "": 1183.2736106193624
    },
    {
      "name": "Burble Enhancer",
      "price": 152951,
      "": 2048.635400283907
    },
    {
      "name": "Crimson Enhancer",
      "price": 317358,
      "": 12641.886234487232
    },
    {
      "name": "Rainbow Enhancer",
      "price": 603150,
      "": -3150.17401035456
    },
    {
      "name": "Holy Enhancer",
      "price": 1199197,
      "": 802.0024308785796
    },
    {
      "name": "Cheese Bulwark",
      "price": 14751,
      "": -6951.842244905285
    },
    {
      "name": "Verdant Bulwark",
      "price": 52132,
      "": -24632.191612462455
    },
    {
      "name": "Azure Bulwark",
      "price": 119727,
      "": -59727.06930955262
    },
    {
      "name": "Burble Bulwark",
      "price": 260905,
      "": -45905.51934336597
    },
    {
      "name": "Crimson Bulwark",
      "price": 537361,
      "": 2638.9114815320354
    },
    {
      "name": "Rainbow Bulwark",
      "price": 1017377,
      "": 32622.22731263144
    },
    {
      "name": "Holy Bulwark",
      "price": 2020882,
      "": -70882.35115836328
    },
    {
      "name": "Cheese Sword",
      "price": 5000,
      "": 0
    },
    {
      "name": "Verdant Sword",
      "price": 34321,
      "": -1321.7180823697418
    },
    {
      "name": "Azure Sword",
      "price": 85572,
      "": 427.1090533416864
    },
    {
      "name": "Burble Sword",
      "price": 192440,
      "": 2559.362396020617
    },
    {
      "name": "Crimson Sword",
      "price": 401509,
      "": 18490.648716746655
    },
    {
      "name": "Rainbow Sword",
      "price": 764683,
      "": 15316.682625402464
    },
    {
      "name": "Holy Sword",
      "price": 1523108,
      "": 26891.74155765609
    },
    {
      "name": "Cheese Spear",
      "price": 5000,
      "": 0
    },
    {
      "name": "Verdant Spear",
      "price": 30535,
      "": -535.3393462459244
    },
    {
      "name": "Azure Spear",
      "price": 79920,
      "": 79.86659194441745
    },
    {
      "name": "Burble Spear",
      "price": 184429,
      "": 5570.987653185992
    },
    {
      "name": "Crimson Spear",
      "price": 393066,
      "": 6933.505921367148
    },
    {
      "name": "Rainbow Spear",
      "price": 748350,
      "": 11649.10623550904
    },
    {
      "name": "Holy Spear",
      "price": 1450946,
      "": -946.502715010196
    },
    {
      "name": "Cheese Mace",
      "price": 5000,
      "": 0
    },
    {
      "name": "Verdant Mace",
      "price": 30551,
      "": 448.9756276446751
    },
    {
      "name": "Azure Mace",
      "price": 79952,
      "": 47.50606175842404
    },
    {
      "name": "Burble Mace",
      "price": 184492,
      "": 5507.30080787593
    },
    {
      "name": "Crimson Mace",
      "price": 393188,
      "": 6811.342001812416
    },
    {
      "name": "Rainbow Mace",
      "price": 748587,
      "": 11412.640310904244
    },
    {
      "name": "Holy Mace",
      "price": 1451407,
      "": -1407.778925707098
    },
    {
      "name": "Cheese Buckler",
      "price": 7797,
      "": -2897.0970590495
    },
    {
      "name": "Verdant Buckler",
      "price": 27249,
      "": -4249.208930511468
    },
    {
      "name": "Azure Buckler",
      "price": 62248,
      "": 3751.745039190777
    },
    {
      "name": "Burble Buckler",
      "price": 134977,
      "": -4977.321742573229
    },
    {
      "name": "Crimson Buckler",
      "price": 276980,
      "": 3019.7301120382617
    },
    {
      "name": "Rainbow Buckler",
      "price": 523939,
      "": -23939.07503076276
    },
    {
      "name": "Holy Buckler",
      "price": 1038518,
      "": -158518.53124259098
    },
    {
      "name": "Cheese Helmet",
      "price": 6638,
      "": -238.43583455970293
    },
    {
      "name": "Verdant Helmet",
      "price": 23103,
      "": 896.6257633660862
    },
    {
      "name": "Azure Helmet",
      "price": 52671,
      "": -671.1957771357484
    },
    {
      "name": "Burble Helmet",
      "price": 113994,
      "": 11005.308869671659
    },
    {
      "name": "Crimson Helmet",
      "price": 233593,
      "": 6406.161744691315
    },
    {
      "name": "Rainbow Helmet",
      "price": 441719,
      "": 18280.61170393112
    },
    {
      "name": "Holy Helmet",
      "price": 874830,
      "": -14830.477160958457
    },
    {
      "name": "Cheese Plate Body",
      "price": 10122,
      "": -322.80816980890995
    },
    {
      "name": "Verdant Plate Body",
      "price": 35564,
      "": -564.9637127503447
    },
    {
      "name": "Azure Plate Body",
      "price": 81452,
      "": 2547.9067206899635
    },
    {
      "name": "Burble Plate Body",
      "price": 177040,
      "": 2959.474829758692
    },
    {
      "name": "Crimson Plate Body",
      "price": 363941,
      "": 16058.770718447573
    },
    {
      "name": "Rainbow Plate Body",
      "price": 688743,
      "": -28743.065550672705
    },
    {
      "name": "Holy Plate Body",
      "price": 1366607,
      "": 33392.88646842982
    },
    {
      "name": "Cheese Plate Legs",
      "price": 8961,
      "": 38.66771756800699
    },
    {
      "name": "Verdant Plate Legs",
      "price": 31411,
      "": -411.0464260039589
    },
    {
      "name": "Azure Plate Legs",
      "price": 71858,
      "": 2141.6536859351327
    },
    {
      "name": "Burble Plate Legs",
      "price": 156025,
      "": 3974.9871561071777
    },
    {
      "name": "Crimson Plate Legs",
      "price": 320491,
      "": 9508.372708183364
    },
    {
      "name": "Rainbow Plate Legs",
      "price": 606400,
      "": 13599.125806772034
    },
    {
      "name": "Holy Plate Legs",
      "price": 1202679,
      "": -2679.5636553294025
    },
    {
      "name": "Cheese Gauntlets",
      "price": 5466,
      "": -66.15403064574093
    },
    {
      "name": "Verdant Gauntlets",
      "price": 18918,
      "": 81.54518293638102
    },
    {
      "name": "Azure Gauntlets",
      "price": 43013,
      "": 1986.4947676274023
    },
    {
      "name": "Burble Gauntlets",
      "price": 92853,
      "": -853.3947468365077
    },
    {
      "name": "Crimson Gauntlets",
      "price": 189903,
      "": 5096.896675930329
    },
    {
      "name": "Rainbow Gauntlets",
      "price": 358910,
      "": 21089.206094790366
    },
    {
      "name": "Holy Gauntlets",
      "price": 709993,
      "": -9993.898238262162
    },
    {
      "name": "Cheese Boots",
      "price": 5466,
      "": -66.15403064574093
    },
    {
      "name": "Verdant Boots",
      "price": 18913,
      "": -413.4634251207608
    },
    {
      "name": "Azure Boots",
      "price": 43000,
      "": 999.6243015017462
    },
    {
      "name": "Burble Boots",
      "price": 92824,
      "": 3175.0026837949263
    },
    {
      "name": "Crimson Boots",
      "price": 189846,
      "": 10153.752629359165
    },
    {
      "name": "Rainbow Boots",
      "price": 358798,
      "": 11201.595958928228
    },
    {
      "name": "Holy Boots",
      "price": 709772,
      "": -9772.489022172522
    },
    {
      "name": "Rough Hood",
      "price": 10349,
      "": -749.7725692535805
    },
    {
      "name": "Reptile Hood",
      "price": 49685,
      "": 2314.842156190185
    },
    {
      "name": "Gobo Hood",
      "price": 105388,
      "": 9611.835672703586
    },
    {
      "name": "Beast Hood",
      "price": 219921,
      "": -44921.108847658994
    },
    {
      "name": "Umbral Hood",
      "price": 583936,
      "": -203936.6019907262
    },
    {
      "name": "Cotton Hat",
      "price": 6457,
      "": 742.6049817668263
    },
    {
      "name": "Linen Hat",
      "price": 15921,
      "": 78.95440108813455
    },
    {
      "name": "Bamboo Hat",
      "price": 36456,
      "": 1543.1264890301245
    },
    {
      "name": "Silk Hat",
      "price": 227026,
      "": 2973.039111524675
    },
    {
      "name": "Radiant Hat",
      "price": 656217,
      "": -116217.14790909353
    },
    {
      "name": "Rough Tunic",
      "price": 16069,
      "": 930.4961935604733
    },
    {
      "name": "Reptile Tunic",
      "price": 77719,
      "": 4280.186107640475
    },
    {
      "name": "Gobo Tunic",
      "price": 163951,
      "": 1048.5264342472947
    },
    {
      "name": "Beast Tunic",
      "price": 340678,
      "": -678.9478367943084
    },
    {
      "name": "Umbral Tunic",
      "price": 910579,
      "": -10579.324008255033
    },
    {
      "name": "Cotton Robe Top",
      "price": 9841,
      "": 158.30027519312898
    },
    {
      "name": "Linen Robe Top",
      "price": 23697,
      "": 4802.765699477226
    },
    {
      "name": "Bamboo Robe Top",
      "price": 53661,
      "": 4338.591740369746
    },
    {
      "name": "Silk Robe Top",
      "price": 352048,
      "": 7951.688897899527
    },
    {
      "name": "Radiant Robe Top",
      "price": 1026228,
      "": 23771.802522357204
    },
    {
      "name": "Rough Chaps",
      "price": 14160,
      "": 339.98162610945656
    },
    {
      "name": "Reptile Chaps",
      "price": 68363,
      "": 3636.0421513139445
    },
    {
      "name": "Gobo Chaps",
      "price": 144399,
      "": 5600.204945227451
    },
    {
      "name": "Beast Chaps",
      "price": 300347,
      "": 9652.35910081939
    },
    {
      "name": "Umbral Chaps",
      "price": 801518,
      "": 18481.569055795437
    },
    {
      "name": "Cotton Robe Bottoms",
      "price": 8710,
      "": -110.68980246197134
    },
    {
      "name": "Linen Robe Bottoms",
      "price": 21094,
      "": 2905.7992941710763
    },
    {
      "name": "Bamboo Robe Bottoms",
      "price": 47895,
      "": 2104.012088084579
    },
    {
      "name": "Silk Robe Bottoms",
      "price": 310295,
      "": -10295.833756323496
    },
    {
      "name": "Radiant Robe Bottoms",
      "price": 902711,
      "": -62711.19522991881
    },
    {
      "name": "Rough Bracers",
      "price": 8440,
      "": -1040.6186242968106
    },
    {
      "name": "Reptile Bracers",
      "price": 40330,
      "": 17669.40198692691
    },
    {
      "name": "Gobo Bracers",
      "price": 85840,
      "": 64159.70512980397
    },
    {
      "name": "Beast Bracers",
      "price": 179600,
      "": -4600.251162525063
    },
    {
      "name": "Umbral Bracers",
      "price": 474901,
      "": -14901.295965437137
    },
    {
      "name": "Cotton Gloves",
      "price": 5326,
      "": -826.7165834804837
    },
    {
      "name": "Linen Gloves",
      "price": 13319,
      "": 1680.6917828452843
    },
    {
      "name": "Bamboo Gloves",
      "price": 30695,
      "": 1304.737782865206
    },
    {
      "name": "Silk Gloves",
      "price": 185284,
      "": 9715.067204821855
    },
    {
      "name": "Radiant Gloves",
      "price": 532725,
      "": -132725.73270013102
    },
    {
      "name": "Rough Boots",
      "price": 8435,
      "": -35.22341840084482
    },
    {
      "name": "Reptile Boots",
      "price": 40302,
      "": 3697.069190303555
    },
    {
      "name": "Gobo Boots",
      "price": 85758,
      "": -1758.7988874972798
    },
    {
      "name": "Beast Boots",
      "price": 179387,
      "": -9387.565544553567
    },
    {
      "name": "Umbral Boots",
      "price": 474414,
      "": -14414.72789084696
    },
    {
      "name": "Cotton Boots",
      "price": 5321,
      "": 1878.678622415484
    },
    {
      "name": "Linen Boots",
      "price": 13291,
      "": -291.6410137780731
    },
    {
      "name": "Bamboo Boots",
      "price": 30613,
      "": -2613.7662344360433
    },
    {
      "name": "Silk Boots",
      "price": 185072,
      "": -5072.247177206649
    },
    {
      "name": "Radiant Boots",
      "price": 532239,
      "": -52239.16462554084
    },
    {
      "name": "Wooden Crossbow",
      "price": 5000,
      "": 0
    },
    {
      "name": "Birch Crossbow",
      "price": 29917,
      "": 1082.5651463078102
    },
    {
      "name": "Cedar Crossbow",
      "price": 86048,
      "": 5951.428383134393
    },
    {
      "name": "Purpleheart Crossbow",
      "price": 210009,
      "": -5009.407520286739
    },
    {
      "name": "Ginkgo Crossbow",
      "price": 459376,
      "": 60623.49548650195
    },
    {
      "name": "Redwood Crossbow",
      "price": 864858,
      "": 35141.51228545874
    },
    {
      "name": "Arcane Crossbow",
      "price": 1535188,
      "": -85188.57269564178
    },
    {
      "name": "Wooden Water Staff",
      "price": 5000,
      "": 0
    },
    {
      "name": "Birch Water Staff",
      "price": 29917,
      "": 2082.56514630781
    },
    {
      "name": "Cedar Water Staff",
      "price": 86048,
      "": 5951.428383134393
    },
    {
      "name": "Purpleheart Water Staff",
      "price": 210009,
      "": 9990.592479713261
    },
    {
      "name": "Ginkgo Water Staff",
      "price": 459376,
      "": 10623.495486501954
    },
    {
      "name": "Redwood Water Staff",
      "price": 864858,
      "": 15141.512285458739
    },
    {
      "name": "Arcane Water Staff",
      "price": 1535188,
      "": -35188.57269564178
    },
    {
      "name": "Wooden Nature Staff",
      "price": 5000,
      "": 0
    },
    {
      "name": "Birch Nature Staff",
      "price": 29937,
      "": 1062.095347631628
    },
    {
      "name": "Cedar Nature Staff",
      "price": 86093,
      "": 5906.374755209734
    },
    {
      "name": "Purpleheart Nature Staff",
      "price": 210100,
      "": 9899.399898083939
    },
    {
      "name": "Ginkgo Nature Staff",
      "price": 459553,
      "": 446.2661254488048
    },
    {
      "name": "Redwood Nature Staff",
      "price": 865203,
      "": -5203.6886624501785
    },
    {
      "name": "Arcane Nature Staff",
      "price": 1535863,
      "": -35863.697612969205
    },
    {
      "name": "Wooden Fire Staff",
      "price": 5000,
      "": 0
    },
    {
      "name": "Birch Fire Staff",
      "price": 29961,
      "": -461.5109713277925
    },
    {
      "name": "Cedar Fire Staff",
      "price": 86142,
      "": 7857.667488170366
    },
    {
      "name": "Purpleheart Fire Staff",
      "price": 210196,
      "": 34803.529277834925
    },
    {
      "name": "Ginkgo Fire Staff",
      "price": 459737,
      "": 262.3362344871857
    },
    {
      "name": "Redwood Fire Staff",
      "price": 865559,
      "": -5559.7852348444285
    },
    {
      "name": "Arcane Fire Staff",
      "price": 1536558,
      "": 63441.49324720516
    },
    {
      "name": "Wooden Bow",
      "price": 5000,
      "": 0
    },
    {
      "name": "Birch Bow",
      "price": 37448,
      "": 4551.320525603849
    },
    {
      "name": "Cedar Bow",
      "price": 111544,
      "": 8455.883612778824
    },
    {
      "name": "Purpleheart Bow",
      "price": 275501,
      "": 104498.08244052902
    },
    {
      "name": "Ginkgo Bow",
      "price": 605667,
      "": 34332.78792017978
    },
    {
      "name": "Redwood Bow",
      "price": 1142052,
      "": -202052.417852361
    },
    {
      "name": "Arcane Bow",
      "price": 2028013,
      "": -328013.7268848908
    },
    {
      "name": "Wooden Shield",
      "price": 5613,
      "": -813.6755633237253
    },
    {
      "name": "Birch Shield",
      "price": 22112,
      "": -7612.486816429624
    },
    {
      "name": "Cedar Shield",
      "price": 60858,
      "": -8858.180625851674
    },
    {
      "name": "Purpleheart Shield",
      "price": 146091,
      "": -16091.16366975868
    },
    {
      "name": "Ginkgo Shield",
      "price": 317207,
      "": -122207.40746613196
    },
    {
      "name": "Redwood Shield",
      "price": 595978,
      "": -225978.88262504386
    },
    {
      "name": "Arcane Shield",
      "price": 1057706,
      "": -337706.6513248519
    }
  ],
  "time": 1783717961.158
}