{
  "train": [
    {
      "name": "Cheese Brush",
      "price": 5000,
      "": 0
    },
    {
      "name": "Verdant Brush",
      "price": 26543,
      "": -543.2795692893815
    },
    {
      "name": "Azure Brush",
      "price": 65723,
      "": 2276.1150227432954
    },
    {
      "name": "Burble Brush",
      "price": 149781,
      "": 5218.378083898831
    },
    {
      "name": "Crimson Brush",
      "price": 316351,
      "": 13648.281786489708
    },
    {
      "name": "Rainbow Brush",
      "price": 592456,
      "": -12456.19168451801
    },
    {
      "name": "Holy Brush",
      "price": 1135181,
      "": -175181.671586219
    },
    {
      "name": "Cheese Shears",
      "price": 5000,
      "": 0
    },
    {
      "name": "Verdant Shears",
      "price": 26543,
      "": -543.2795692893815
    },
    {
      "name": "Azure Shears",
      "price": 65723,
      "": -1723.8849772567046
    },
    {
      "name": "Burble Shears",
      "price": 149781,
      "": 5218.378083898831
    },
    {
      "name": "Crimson Shears",
      "price": 316351,
      "": 13648.281786489708
    },
    {
      "name": "Rainbow Shears",
      "price": 592456,
      "": 47543.80831548199
    },
    {
      "name": "Holy Shears",
      "price": 1135181,
      "": 14818.328413781011
    },
    {
      "name": "Cheese Hatchet",
      "price": 5000,
      "": 0
    },
    {
      "name": "Verdant Hatchet",
      "price": 26543,
      "": -543.2795692893815
    },
    {
      "name": "Azure Hatchet",
      "price": 65723,
      "": 4276.115022743295
    },
    {
      "name": "Burble Hatchet",
      "price": 149781,
      "": 10218.378083898831
    },
    {
      "name": "Crimson Hatchet",
      "price": 316351,
      "": 13648.281786489708
    },
    {
      "name": "Rainbow Hatchet",
      "price": 592456,
      "": 27543.80831548199
    },
    {
      "name": "Holy Hatchet",
      "price": 1135181,
      "": -35181.67158621899
    },
    {
      "name": "Cheese Hammer",
      "price": 5000,
      "": 0
    },
    {
      "name": "Verdant Hammer",
      "price": 26558,
      "": -58.00866076476814
    },
    {
      "name": "Azure Hammer",
      "price": 65754,
      "": -1754.2684266025462
    },
    {
      "name": "Burble Hammer",
      "price": 149841,
      "": 10158.597867294331
    },
    {
      "name": "Crimson Hammer",
      "price": 316466,
      "": 3533.649812521646
    },
    {
      "name": "Rainbow Hammer",
      "price": 592677,
      "": 27322.01195064513
    },
    {
      "name": "Holy Hammer",
      "price": 1135614,
      "": -85614.12555215065
    },
    {
      "name": "Cheese Chisel",
      "price": 5000,
      "": 0
    },
    {
      "name": "Verdant Chisel",
      "price": 26558,
      "": -558.0086607647681
    },
    {
      "name": "Azure Chisel",
      "price": 65754,
      "": 4245.731573397454
    },
    {
      "name": "Burble Chisel",
      "price": 149841,
      "": 10158.597867294331
    },
    {
      "name": "Crimson Chisel",
      "price": 316466,
      "": 13533.649812521646
    },
    {
      "name": "Rainbow Chisel",
      "price": 592677,
      "": 7322.01195064513
    },
    {
      "name": "Holy Chisel",
      "price": 1135614,
      "": -35614.125552150654
    },
    {
      "name": "Cheese Spatula",
      "price": 5000,
      "": 0
    },
    {
      "name": "Verdant Spatula",
      "price": 28241,
      "": -241.6882526014997
    },
    {
      "name": "Azure Spatula",
      "price": 68524,
      "": 1475.8070836015395
    },
    {
      "name": "Burble Spatula",
      "price": 154295,
      "": 5704.993785661674
    },
    {
      "name": "Crimson Spatula",
      "price": 323934,
      "": 16065.71613905218
    },
    {
      "name": "Rainbow Spatula",
      "price": 608853,
      "": 11146.015011869487
    },
    {
      "name": "Holy Spatula",
      "price": 1180466,
      "": -30466.98779704864
    },
    {
      "name": "Cheese Needle",
      "price": 5000,
      "": 0
    },
    {
      "name": "Verdant Needle",
      "price": 28241,
      "": -241.6882526014997
    },
    {
      "name": "Azure Needle",
      "price": 68524,
      "": 3475.8070836015395
    },
    {
      "name": "Burble Needle",
      "price": 154295,
      "": 704.9937856616743
    },
    {
      "name": "Crimson Needle",
      "price": 323934,
      "": -3934.2838609478204
    },
    {
      "name": "Rainbow Needle",
      "price": 608853,
      "": -8853.984988130513
    },
    {
      "name": "Holy Needle",
      "price": 1180466,
      "": -130466.98779704864
    },
    {
      "name": "Cheese Pot",
      "price": 5000,
      "": 0
    },
    {
      "name": "Verdant Pot",
      "price": 28241,
      "": -241.6882526014997
    },
    {
      "name": "Azure Pot",
      "price": 68524,
      "": 3475.8070836015395
    },
    {
      "name": "Burble Pot",
      "price": 154295,
      "": 5704.993785661674
    },
    {
      "name": "Crimson Pot",
      "price": 323934,
      "": 16065.71613905218
    },
    {
      "name": "Rainbow Pot",
      "price": 608853,
      "": 31146.015011869487
    },
    {
      "name": "Holy Pot",
      "price": 1180466,
      "": -30466.98779704864
    },
    {
      "name": "Cheese Alembic",
      "price": 5000,
      "": 0
    },
    {
      "name": "Verdant Alembic",
      "price": 28256,
      "": -256.6146197711678
    },
    {
      "name": "Azure Alembic",
      "price": 68554,
      "": -554.9931668609788
    },
    {
      "name": "Burble Alembic",
      "price": 154355,
      "": 5644.361647051497
    },
    {
      "name": "Crimson Alembic",
      "price": 324050,
      "": 15949.372632400424
    },
    {
      "name": "Rainbow Alembic",
      "price": 609079,
      "": 30920.72282545676
    },
    {
      "name": "Holy Alembic",
      "price": 1180906,
      "": 19093.321381859947
    },
    {
      "name": "Cheese Enhancer",
      "price": 5000,
      "": 0
    },
    {
      "name": "Verdant Enhancer",
      "price": 28256,
      "": -256.6146197711678
    },
    {
      "name": "Azure Enhancer",
      "price": 68554,
      "": 3445.006833139021
    },
    {
      "name": "Burble Enhancer",
      "price": 154355,
      "": 5644.361647051497
    },
    {
      "name": "Crimson Enhancer",
      "price": 324050,
      "": 15949.372632400424
    },
    {
      "name": "Rainbow Enhancer",
      "price": 609079,
      "": 10920.72282545676
    },
    {
      "name": "Holy Enhancer",
      "price": 1180906,
      "": -80906.67861814005
    },
    {
      "name": "Cheese Bulwark",
      "price": 14270,
      "": -4870.973575452224
    },
    {
      "name": "Verdant Bulwark",
      "price": 51567,
      "": -51568.41629006749
    },
    {
      "name": "Azure Bulwark",
      "price": 119029,
      "": -43029.93799792453
    },
    {
      "name": "Burble Bulwark",
      "price": 263231,
      "": -53231.32859392767
    },
    {
      "name": "Crimson Bulwark",
      "price": 549046,
      "": -189046.92545555264
    },
    {
      "name": "Rainbow Bulwark",
      "price": 1028297,
      "": -208297.00820495537
    },
    {
      "name": "Holy Bulwark",
      "price": 1991281,
      "": -91281.20639973157
    },
    {
      "name": "Cheese Sword",
      "price": 5000,
      "": 0
    },
    {
      "name": "Verdant Sword",
      "price": 34194,
      "": -2194.014314102751
    },
    {
      "name": "Azure Sword",
      "price": 85315,
      "": 684.4326754524664
    },
    {
      "name": "Burble Sword",
      "price": 194396,
      "": 603.2890160912648
    },
    {
      "name": "Crimson Sword",
      "price": 410390,
      "": 9609.003457166255
    },
    {
      "name": "Rainbow Sword",
      "price": 772817,
      "": 27182.8832457792
    },
    {
      "name": "Holy Sword",
      "price": 1500534,
      "": -534.7708894473035
    },
    {
      "name": "Cheese Spear",
      "price": 5000,
      "": 0
    },
    {
      "name": "Verdant Spear",
      "price": 30841,
      "": 158.712952190137
    },
    {
      "name": "Azure Spear",
      "price": 79805,
      "": 2194.103438730337
    },
    {
      "name": "Burble Spear",
      "price": 185548,
      "": 4451.136194913386
    },
    {
      "name": "Crimson Spear",
      "price": 395568,
      "": 4431.080425965891
    },
    {
      "name": "Rainbow Spear",
      "price": 740685,
      "": 19314.79810604453
    },
    {
      "name": "Holy Spear",
      "price": 1411257,
      "": -11257.94911355176
    },
    {
      "name": "Cheese Mace",
      "price": 5000,
      "": 0
    },
    {
      "name": "Verdant Mace",
      "price": 30856,
      "": -1356.1142848827076
    },
    {
      "name": "Azure Mace",
      "price": 79836,
      "": 163.51265427617182
    },
    {
      "name": "Burble Mace",
      "price": 185609,
      "": 4390.932281496382
    },
    {
      "name": "Crimson Mace",
      "price": 395684,
      "": 14315.597456135205
    },
    {
      "name": "Rainbow Mace",
      "price": 740908,
      "": -908.7358746647369
    },
    {
      "name": "Holy Mace",
      "price": 1411693,
      "": -11693.998864719644
    },
    {
      "name": "Cheese Buckler",
      "price": 7533,
      "": -2133.6292847637887
    },
    {
      "name": "Verdant Buckler",
      "price": 26902,
      "": -1402.118701403826
    },
    {
      "name": "Azure Buckler",
      "price": 61769,
      "": -1769.2727586977198
    },
    {
      "name": "Burble Buckler",
      "price": 135892,
      "": -5892.785291724023
    },
    {
      "name": "Crimson Buckler",
      "price": 282369,
      "": -7369.289612497494
    },
    {
      "name": "Rainbow Buckler",
      "price": 528564,
      "": -168564.68431740045
    },
    {
      "name": "Holy Buckler",
      "price": 1022182,
      "": -382182.4531079361
    },
    {
      "name": "Cheese Helmet",
      "price": 6411,
      "": 388.8237764607011
    },
    {
      "name": "Verdant Helmet",
      "price": 22792,
      "": 707.5078292084254
    },
    {
      "name": "Azure Helmet",
      "price": 52228,
      "": 3771.5782617104414
    },
    {
      "name": "Burble Helmet",
      "price": 114674,
      "": 10325.198381745373
    },
    {
      "name": "Crimson Helmet",
      "price": 237932,
      "": 7067.1787548493885
    },
    {
      "name": "Rainbow Helmet",
      "price": 445294,
      "": 4705.039151987352
    },
    {
      "name": "Holy Helmet",
      "price": 860703,
      "": -703.0969854869181
    },
    {
      "name": "Cheese Plate Body",
      "price": 9786,
      "": -1786.4653064724625
    },
    {
      "name": "Verdant Plate Body",
      "price": 35144,
      "": 855.8600346595558
    },
    {
      "name": "Azure Plate Body",
      "price": 80897,
      "": 3102.0243540820957
    },
    {
      "name": "Burble Plate Body",
      "price": 178421,
      "": 11578.661460884643
    },
    {
      "name": "Crimson Plate Body",
      "price": 371420,
      "": 8579.964201481722
    },
    {
      "name": "Rainbow Plate Body",
      "price": 695448,
      "": 24551.192017678637
    },
    {
      "name": "Holy Plate Body",
      "price": 1345814,
      "": 4185.324593912577
    },
    {
      "name": "Cheese Plate Legs",
      "price": 8661,
      "": 338.6484882194982
    },
    {
      "name": "Verdant Plate Legs",
      "price": 31026,
      "": 973.1271340406165
    },
    {
      "name": "Azure Plate Legs",
      "price": 71341,
      "": 4658.650527930062
    },
    {
      "name": "Burble Plate Legs",
      "price": 157172,
      "": 12827.728600009403
    },
    {
      "name": "Crimson Plate Legs",
      "price": 326923,
      "": 13076.148239934933
    },
    {
      "name": "Rainbow Plate Legs",
      "price": 612063,
      "": 27936.720527579426
    },
    {
      "name": "Holy Plate Legs",
      "price": 1184108,
      "": 15891.07886832091
    },
    {
      "name": "Cheese Gauntlets",
      "price": 5275,
      "": -75.84747063390296
    },
    {
      "name": "Verdant Gauntlets",
      "price": 18645,
      "": 854.0816042645893
    },
    {
      "name": "Azure Gauntlets",
      "price": 42611,
      "": 3388.6510427994144
    },
    {
      "name": "Burble Gauntlets",
      "price": 93306,
      "": 2693.1706487443153
    },
    {
      "name": "Crimson Gauntlets",
      "price": 193208,
      "": 6791.308559207071
    },
    {
      "name": "Rainbow Gauntlets",
      "price": 361468,
      "": 18531.4638580241
    },
    {
      "name": "Holy Gauntlets",
      "price": 698138,
      "": -38138.027011896134
    },
    {
      "name": "Cheese Boots",
      "price": 5275,
      "": -75.84747063390296
    },
    {
      "name": "Verdant Boots",
      "price": 18641,
      "": -141.1999750490795
    },
    {
      "name": "Azure Boots",
      "price": 42598,
      "": 1401.0625434276517
    },
    {
      "name": "Burble Boots",
      "price": 93279,
      "": 720.0150692314201
    },
    {
      "name": "Crimson Boots",
      "price": 193154,
      "": 6845.055151314271
    },
    {
      "name": "Rainbow Boots",
      "price": 361362,
      "": 18637.707299924223
    },
    {
      "name": "Holy Boots",
      "price": 697928,
      "": -17928.726312351762
    },
    {
      "name": "Rough Hood",
      "price": 10303,
      "": -303.55377455970665
    },
    {
      "name": "Reptile Hood",
      "price": 48612,
      "": 1387.7836454952558
    },
    {
      "name": "Gobo Hood",
      "price": 100872,
      "": 14127.066642678867
    },
    {
      "name": "Beast Hood",
      "price": 206638,
      "": 23361.107809279754
    },
    {
      "name": "Umbral Hood",
      "price": 569459,
      "": -169459.53393784852
    },
    {
      "name": "Cotton Hat",
      "price": 6230,
      "": -1330.1354072127679
    },
    {
      "name": "Linen Hat",
      "price": 15572,
      "": 1927.7326250870938
    },
    {
      "name": "Bamboo Hat",
      "price": 36784,
      "": 215.5156222706937
    },
    {
      "name": "Silk Hat",
      "price": 221303,
      "": -1303.1983131692396
    },
    {
      "name": "Radiant Hat",
      "price": 641151,
      "": -61151.69720315456
    },
    {
      "name": "Rough Tunic",
      "price": 16022,
      "": -522.3582881520015
    },
    {
      "name": "Reptile Tunic",
      "price": 76100,
      "": 7899.7418964462995
    },
    {
      "name": "Gobo Tunic",
      "price": 156982,
      "": 3017.523599288019
    },
    {
      "name": "Beast Tunic",
      "price": 320039,
      "": 9960.371635593881
    },
    {
      "name": "Umbral Tunic",
      "price": 888713,
      "": 11286.817553862813
    },
    {
      "name": "Cotton Robe Top",
      "price": 9504,
      "": -504.88890039689795
    },
    {
      "name": "Linen Robe Top",
      "price": 23236,
      "": 4763.660263793245
    },
    {
      "name": "Bamboo Robe Top",
      "price": 54440,
      "": -2440.95803336503
    },
    {
      "name": "Silk Robe Top",
      "price": 343502,
      "": -13502.518160324427
    },
    {
      "name": "Radiant Robe Top",
      "price": 1003420,
      "": -63420.64367062703
    },
    {
      "name": "Rough Chaps",
      "price": 14113,
      "": -113.34081667654573
    },
    {
      "name": "Reptile Chaps",
      "price": 66927,
      "": 1072.7932038709405
    },
    {
      "name": "Gobo Chaps",
      "price": 138250,
      "": 6749.60792371197
    },
    {
      "name": "Beast Chaps",
      "price": 282164,
      "": 2835.007322047546
    },
    {
      "name": "Umbral Chaps",
      "price": 782125,
      "": -22125.157017110265
    },
    {
      "name": "Cotton Robe Bottoms",
      "price": 8410,
      "": 189.44489760916804
    },
    {
      "name": "Linen Robe Bottoms",
      "price": 20671,
      "": 2328.7217752995093
    },
    {
      "name": "Bamboo Robe Bottoms",
      "price": 48526,
      "": 473.43649514056597
    },
    {
      "name": "Silk Robe Bottoms",
      "price": 302695,
      "": -2695.0212493810104
    },
    {
      "name": "Radiant Robe Bottoms",
      "price": 882494,
      "": -22494.18558853888
    },
    {
      "name": "Rough Bracers",
      "price": 8394,
      "": -194.84966214927044
    },
    {
      "name": "Reptile Bracers",
      "price": 39440,
      "": 2559.609627799262
    },
    {
      "name": "Gobo Bracers",
      "price": 82144,
      "": -144.44977570144692
    },
    {
      "name": "Beast Bracers",
      "price": 168774,
      "": 1225.865696189372
    },
    {
      "name": "Umbral Bracers",
      "price": 462895,
      "": 7104.303766716679
    },
    {
      "name": "Cotton Gloves",
      "price": 5136,
      "": 63.88503172828314
    },
    {
      "name": "Linen Gloves",
      "price": 13008,
      "": 2991.5688114727363
    },
    {
      "name": "Bamboo Gloves",
      "price": 30873,
      "": 8126.309407972036
    },
    {
      "name": "Silk Gloves",
      "price": 180505,
      "": 9494.420798230218
    },
    {
      "name": "Radiant Gloves",
      "price": 520249,
      "": -150249.42684552824
    },
    {
      "name": "Rough Boots",
      "price": 8389,
      "": -189.74951145023078
    },
    {
      "name": "Reptile Boots",
      "price": 39414,
      "": 1585.7637559943178
    },
    {
      "name": "Gobo Boots",
      "price": 82067,
      "": 3932.589321812993
    },
    {
      "name": "Beast Boots",
      "price": 168573,
      "": -3573.0801227303746
    },
    {
      "name": "Umbral Boots",
      "price": 462435,
      "": 7564.262210120272
    },
    {
      "name": "Cotton Boots",
      "price": 5131,
      "": -231.0148175726781
    },
    {
      "name": "Linen Boots",
      "price": 12982,
      "": 517.7229396677903
    },
    {
      "name": "Bamboo Boots",
      "price": 30796,
      "": -1296.651494513524
    },
    {
      "name": "Silk Boots",
      "price": 180304,
      "": 9695.474979310442
    },
    {
      "name": "Radiant Boots",
      "price": 519789,
      "": -39789.46840212465
    },
    {
      "name": "Wooden Crossbow",
      "price": 5000,
      "": 0
    },
    {
      "name": "Birch Crossbow",
      "price": 29790,
      "": -290.0040566817297
    },
    {
      "name": "Cedar Crossbow",
      "price": 85791,
      "": 10208.033971999073
    },
    {
      "name": "Purpleheart Crossbow",
      "price": 199746,
      "": -9746.778808319621
    },
    {
      "name": "Ginkgo Crossbow",
      "price": 419380,
      "": 10619.7612737632
    },
    {
      "name": "Redwood Crossbow",
      "price": 781753,
      "": 18246.137912169215
    },
    {
      "name": "Arcane Crossbow",
      "price": 1436046,
      "": 13953.071646832163
    },
    {
      "name": "Wooden Water Staff",
      "price": 5000,
      "": 0
    },
    {
      "name": "Birch Water Staff",
      "price": 29790,
      "": -790.0040566817297
    },
    {
      "name": "Cedar Water Staff",
      "price": 85791,
      "": 2208.0339719990734
    },
    {
      "name": "Purpleheart Water Staff",
      "price": 199746,
      "": 35253.22119168038
    },
    {
      "name": "Ginkgo Water Staff",
      "price": 419380,
      "": 10619.7612737632
    },
    {
      "name": "Redwood Water Staff",
      "price": 781753,
      "": 18246.137912169215
    },
    {
      "name": "Arcane Water Staff",
      "price": 1436046,
      "": -36046.92835316784
    },
    {
      "name": "Wooden Nature Staff",
      "price": 5000,
      "": 0
    },
    {
      "name": "Birch Nature Staff",
      "price": 29809,
      "": -309.35439474863597
    },
    {
      "name": "Cedar Nature Staff",
      "price": 85834,
      "": 4165.444255056864
    },
    {
      "name": "Purpleheart Nature Staff",
      "price": 199832,
      "": 25167.015786750126
    },
    {
      "name": "Ginkgo Nature Staff",
      "price": 419547,
      "": 10452.224303516909
    },
    {
      "name": "Redwood Nature Staff",
      "price": 782080,
      "": -2080.1845470167464
    },
    {
      "name": "Arcane Nature Staff",
      "price": 1436685,
      "": -36685.131766612874
    },
    {
      "name": "Wooden Fire Staff",
      "price": 5000,
      "": 0
    },
    {
      "name": "Birch Fire Staff",
      "price": 29831,
      "": -331.66972181198435
    },
    {
      "name": "Cedar Fire Staff",
      "price": 85880,
      "": -7880.599289309976
    },
    {
      "name": "Purpleheart Fire Staff",
      "price": 199923,
      "": 30076.388177663757
    },
    {
      "name": "Ginkgo Fire Staff",
      "price": 419721,
      "": 278.3532446453464
    },
    {
      "name": "Redwood Fire Staff",
      "price": 782416,
      "": 17583.193233620026
    },
    {
      "name": "Arcane Fire Staff",
      "price": 1437341,
      "": -87341.94290385419
    },
    {
      "name": "Wooden Bow",
      "price": 5000,
      "": 0
    },
    {
      "name": "Birch Bow",
      "price": 37319,
      "": 2680.7285722601446
    },
    {
      "name": "Cedar Bow",
      "price": 111283,
      "": 8716.722858357782
    },
    {
      "name": "Purpleheart Bow",
      "price": 261972,
      "": 13027.915954965749
    },
    {
      "name": "Ginkgo Bow",
      "price": 552619,
      "": -32619.634176517837
    },
    {
      "name": "Redwood Bow",
      "price": 1031759,
      "": -71759.8593440525
    },
    {
      "name": "Arcane Bow",
      "price": 1896765,
      "": -296765.7100892095
    },
    {
      "name": "Wooden Shield",
      "price": 5676,
      "": -876.6790956356226
    },
    {
      "name": "Birch Shield",
      "price": 22092,
      "": -8092.985691738362
    },
    {
      "name": "Cedar Shield",
      "price": 60708,
      "": -8708.611507868955
    },
    {
      "name": "Purpleheart Shield",
      "price": 139097,
      "": -19097.854569162388
    },
    {
      "name": "Ginkgo Shield",
      "price": 289969,
      "": -19969.2141318777
    },
    {
      "name": "Redwood Shield",
      "price": 539336,
      "": -99336.72025594662
    },
    {
      "name": "Arcane Shield",
      "price": 989761,
      "": -269761.4328107089
    }
  ],
  "time": 1782809860.334
}