{
  "train": [
    {
      "name": "Cheese Brush",
      "price": 5000,
      "": 0
    },
    {
      "name": "Verdant Brush",
      "price": 26445,
      "": -945.8956635521208
    },
    {
      "name": "Azure Brush",
      "price": 67303,
      "": 2696.5124274469854
    },
    {
      "name": "Burble Brush",
      "price": 150947,
      "": 9052.964160149684
    },
    {
      "name": "Crimson Brush",
      "price": 314457,
      "": 5542.858468111546
    },
    {
      "name": "Rainbow Brush",
      "price": 603807,
      "": -23807.264299810864
    },
    {
      "name": "Holy Brush",
      "price": 1184455,
      "": 15544.45326223271
    },
    {
      "name": "Cheese Shears",
      "price": 5000,
      "": 0
    },
    {
      "name": "Verdant Shears",
      "price": 26445,
      "": -445.8956635521208
    },
    {
      "name": "Azure Shears",
      "price": 67303,
      "": 696.5124274469854
    },
    {
      "name": "Burble Shears",
      "price": 150947,
      "": 4052.964160149684
    },
    {
      "name": "Crimson Shears",
      "price": 314457,
      "": 5542.858468111546
    },
    {
      "name": "Rainbow Shears",
      "price": 603807,
      "": 16192.735700189136
    },
    {
      "name": "Holy Shears",
      "price": 1184455,
      "": 15544.45326223271
    },
    {
      "name": "Cheese Hatchet",
      "price": 5000,
      "": 0
    },
    {
      "name": "Verdant Hatchet",
      "price": 26445,
      "": -945.8956635521208
    },
    {
      "name": "Azure Hatchet",
      "price": 67303,
      "": -1303.4875725530146
    },
    {
      "name": "Burble Hatchet",
      "price": 150947,
      "": 4052.964160149684
    },
    {
      "name": "Crimson Hatchet",
      "price": 314457,
      "": -4457.141531888454
    },
    {
      "name": "Rainbow Hatchet",
      "price": 603807,
      "": -3807.264299810864
    },
    {
      "name": "Holy Hatchet",
      "price": 1184455,
      "": 15544.45326223271
    },
    {
      "name": "Cheese Hammer",
      "price": 5000,
      "": 0
    },
    {
      "name": "Verdant Hammer",
      "price": 26460,
      "": -460.69951155769013
    },
    {
      "name": "Azure Hammer",
      "price": 67334,
      "": 665.9747689123615
    },
    {
      "name": "Burble Hammer",
      "price": 151007,
      "": 8992.880533007294
    },
    {
      "name": "Crimson Hammer",
      "price": 314572,
      "": -14572.35531286319
    },
    {
      "name": "Rainbow Hammer",
      "price": 604030,
      "": 15969.813622563495
    },
    {
      "name": "Holy Hammer",
      "price": 1184890,
      "": 15109.804404782131
    },
    {
      "name": "Cheese Chisel",
      "price": 5000,
      "": 0
    },
    {
      "name": "Verdant Chisel",
      "price": 26460,
      "": 39.30048844230987
    },
    {
      "name": "Azure Chisel",
      "price": 67334,
      "": 2665.9747689123615
    },
    {
      "name": "Burble Chisel",
      "price": 151007,
      "": 8992.880533007294
    },
    {
      "name": "Crimson Chisel",
      "price": 314572,
      "": 5427.64468713681
    },
    {
      "name": "Rainbow Chisel",
      "price": 604030,
      "": -4030.1863774365047
    },
    {
      "name": "Holy Chisel",
      "price": 1184890,
      "": 15109.804404782131
    },
    {
      "name": "Cheese Spatula",
      "price": 5000,
      "": 0
    },
    {
      "name": "Verdant Spatula",
      "price": 28253,
      "": 246.99640680965604
    },
    {
      "name": "Azure Spatula",
      "price": 69814,
      "": 2185.715585238897
    },
    {
      "name": "Burble Spatula",
      "price": 155605,
      "": 9394.443798313412
    },
    {
      "name": "Crimson Spatula",
      "price": 322429,
      "": -22429.526741434587
    },
    {
      "name": "Rainbow Spatula",
      "price": 623890,
      "": 16109.636071543093
    },
    {
      "name": "Holy Spatula",
      "price": 1241248,
      "": 8751.798282332951
    },
    {
      "name": "Cheese Needle",
      "price": 5000,
      "": 0
    },
    {
      "name": "Verdant Needle",
      "price": 28253,
      "": -253.00359319034396
    },
    {
      "name": "Azure Needle",
      "price": 69814,
      "": 2185.715585238897
    },
    {
      "name": "Burble Needle",
      "price": 155605,
      "": 9394.443798313412
    },
    {
      "name": "Crimson Needle",
      "price": 322429,
      "": 7570.473258565413
    },
    {
      "name": "Rainbow Needle",
      "price": 623890,
      "": 16109.636071543093
    },
    {
      "name": "Holy Needle",
      "price": 1241248,
      "": 8751.798282332951
    },
    {
      "name": "Cheese Pot",
      "price": 5000,
      "": 0
    },
    {
      "name": "Verdant Pot",
      "price": 28253,
      "": -253.00359319034396
    },
    {
      "name": "Azure Pot",
      "price": 69814,
      "": 2185.715585238897
    },
    {
      "name": "Burble Pot",
      "price": 155605,
      "": 4394.443798313412
    },
    {
      "name": "Crimson Pot",
      "price": 322429,
      "": -22429.526741434587
    },
    {
      "name": "Rainbow Pot",
      "price": 623890,
      "": -3890.363928456907
    },
    {
      "name": "Holy Pot",
      "price": 1241248,
      "": 8751.798282332951
    },
    {
      "name": "Cheese Alembic",
      "price": 5000,
      "": 0
    },
    {
      "name": "Verdant Alembic",
      "price": 28268,
      "": -268.00571814993964
    },
    {
      "name": "Azure Alembic",
      "price": 69845,
      "": 2154.7590101410606
    },
    {
      "name": "Burble Alembic",
      "price": 155666,
      "": 9333.50392529156
    },
    {
      "name": "Crimson Alembic",
      "price": 322546,
      "": -22546.460741863935
    },
    {
      "name": "Rainbow Alembic",
      "price": 624116,
      "": -24116.799570469884
    },
    {
      "name": "Holy Alembic",
      "price": 1241690,
      "": 58309.87583954306
    },
    {
      "name": "Cheese Enhancer",
      "price": 5000,
      "": 0
    },
    {
      "name": "Verdant Enhancer",
      "price": 28268,
      "": -268.00571814993964
    },
    {
      "name": "Azure Enhancer",
      "price": 69845,
      "": 154.75901014106057
    },
    {
      "name": "Burble Enhancer",
      "price": 155666,
      "": 4333.503925291559
    },
    {
      "name": "Crimson Enhancer",
      "price": 322546,
      "": 17453.539258136065
    },
    {
      "name": "Rainbow Enhancer",
      "price": 624116,
      "": 15883.200429530116
    },
    {
      "name": "Holy Enhancer",
      "price": 1241690,
      "": 8309.875839543063
    },
    {
      "name": "Cheese Bulwark",
      "price": 14275,
      "": -5675.041722705442
    },
    {
      "name": "Verdant Bulwark",
      "price": 51578,
      "": -20578.845649122493
    },
    {
      "name": "Azure Bulwark",
      "price": 121225,
      "": -25225.468871823876
    },
    {
      "name": "Burble Bulwark",
      "price": 265447,
      "": -55447.54591501702
    },
    {
      "name": "Crimson Bulwark",
      "price": 546411,
      "": -126411.55229341844
    },
    {
      "name": "Rainbow Bulwark",
      "price": 1053971,
      "": -153971.2570736094
    },
    {
      "name": "Holy Bulwark",
      "price": 2095289,
      "": -295289.2767156274
    },
    {
      "name": "Cheese Sword",
      "price": 5000,
      "": 0
    },
    {
      "name": "Verdant Sword",
      "price": 34205,
      "": -1205.2178891845833
    },
    {
      "name": "Azure Sword",
      "price": 86967,
      "": 3032.4900783094927
    },
    {
      "name": "Burble Sword",
      "price": 196068,
      "": 3931.1109188703995
    },
    {
      "name": "Crimson Sword",
      "price": 408432,
      "": 1567.2321303271456
    },
    {
      "name": "Rainbow Sword",
      "price": 792106,
      "": 7893.727166507393
    },
    {
      "name": "Holy Sword",
      "price": 1578602,
      "": 21397.896077937447
    },
    {
      "name": "Cheese Spear",
      "price": 5000,
      "": 0
    },
    {
      "name": "Verdant Spear",
      "price": 30635,
      "": -1635.3159066293447
    },
    {
      "name": "Azure Spear",
      "price": 82037,
      "": -37.3229381996498
    },
    {
      "name": "Burble Spear",
      "price": 186931,
      "": 8068.322121062258
    },
    {
      "name": "Crimson Spear",
      "price": 392832,
      "": 17167.20707378816
    },
    {
      "name": "Rainbow Spear",
      "price": 752607,
      "": 27392.886254757526
    },
    {
      "name": "Holy Spear",
      "price": 1466317,
      "": -16317.171258438844
    },
    {
      "name": "Cheese Mace",
      "price": 5000,
      "": 0
    },
    {
      "name": "Verdant Mace",
      "price": 30650,
      "": -650.2183983638643
    },
    {
      "name": "Azure Mace",
      "price": 82068,
      "": -2068.0689841582353
    },
    {
      "name": "Burble Mace",
      "price": 186992,
      "": 8007.812646662205
    },
    {
      "name": "Crimson Mace",
      "price": 392948,
      "": 7051.137977777573
    },
    {
      "name": "Rainbow Mace",
      "price": 752831,
      "": 7168.217742104898
    },
    {
      "name": "Holy Mace",
      "price": 1466755,
      "": 33244.56584870443
    },
    {
      "name": "Cheese Buckler",
      "price": 7537,
      "": -2837.6841043166614
    },
    {
      "name": "Verdant Buckler",
      "price": 26913,
      "": -913.5097997825978
    },
    {
      "name": "Azure Buckler",
      "price": 62878,
      "": -878.4797653691348
    },
    {
      "name": "Burble Buckler",
      "price": 137022,
      "": 7977.397802842606
    },
    {
      "name": "Crimson Buckler",
      "price": 281091,
      "": -1091.424007170077
    },
    {
      "name": "Rainbow Buckler",
      "price": 541474,
      "": -171474.9771214903
    },
    {
      "name": "Holy Buckler",
      "price": 1074321,
      "": -174321.199670661
    },
    {
      "name": "Cheese Helmet",
      "price": 6415,
      "": 384.7689569078284
    },
    {
      "name": "Verdant Helmet",
      "price": 22803,
      "": 1196.1167308296535
    },
    {
      "name": "Azure Helmet",
      "price": 53156,
      "": 4843.412071365565
    },
    {
      "name": "Burble Helmet",
      "price": 115623,
      "": 4376.422292638512
    },
    {
      "name": "Crimson Helmet",
      "price": 236881,
      "": 3118.743339768669
    },
    {
      "name": "Rainbow Helmet",
      "price": 456078,
      "": 13921.975939734082
    },
    {
      "name": "Holy Helmet",
      "price": 904197,
      "": -24197.144568620017
    },
    {
      "name": "Cheese Plate Body",
      "price": 9790,
      "": 209.43962629514317
    },
    {
      "name": "Verdant Plate Body",
      "price": 35155,
      "": -155.64662222709012
    },
    {
      "name": "Azure Plate Body",
      "price": 82369,
      "": -369.5028349315253
    },
    {
      "name": "Burble Plate Body",
      "price": 179913,
      "": 10086.293009180372
    },
    {
      "name": "Crimson Plate Body",
      "price": 369690,
      "": 10309.529387508577
    },
    {
      "name": "Rainbow Plate Body",
      "price": 712615,
      "": 7384.690645974944
    },
    {
      "name": "Holy Plate Body",
      "price": 1415246,
      "": -15246.238283751998
    },
    {
      "name": "Cheese Plate Legs",
      "price": 8665,
      "": 334.5669253639426
    },
    {
      "name": "Verdant Plate Legs",
      "price": 31038,
      "": 961.6592563557097
    },
    {
      "name": "Azure Plate Legs",
      "price": 72631,
      "": 5368.2442209915025
    },
    {
      "name": "Burble Plate Legs",
      "price": 158483,
      "": 6516.558726706979
    },
    {
      "name": "Crimson Plate Legs",
      "price": 325420,
      "": 4579.715488495072
    },
    {
      "name": "Rainbow Plate Legs",
      "price": 627101,
      "": 12898.036508540856
    },
    {
      "name": "Holy Plate Legs",
      "price": 1244894,
      "": -44894.63596089673
    },
    {
      "name": "Cheese Gauntlets",
      "price": 5279,
      "": 120.1630595352608
    },
    {
      "name": "Verdant Gauntlets",
      "price": 18657,
      "": 342.87802918276066
    },
    {
      "name": "Azure Gauntlets",
      "price": 43358,
      "": 2641.9125272890815
    },
    {
      "name": "Burble Gauntlets",
      "price": 94073,
      "": 5926.196633156127
    },
    {
      "name": "Crimson Gauntlets",
      "price": 192381,
      "": 7618.032130327134
    },
    {
      "name": "Rainbow Gauntlets",
      "price": 370121,
      "": 19878.45573793596
    },
    {
      "name": "Holy Gauntlets",
      "price": 732981,
      "": -52981.86514655221
    },
    {
      "name": "Cheese Boots",
      "price": 5279,
      "": -79.8369404647392
    },
    {
      "name": "Verdant Boots",
      "price": 18652,
      "": 347.6203979013917
    },
    {
      "name": "Azure Boots",
      "price": 43345,
      "": 2654.387021668357
    },
    {
      "name": "Burble Boots",
      "price": 94046,
      "": 3953.1773007249576
    },
    {
      "name": "Crimson Boots",
      "price": 192327,
      "": 2672.051509709854
    },
    {
      "name": "Rainbow Boots",
      "price": 370014,
      "": 9985.238411402737
    },
    {
      "name": "Holy Boots",
      "price": 732771,
      "": 7228.497844857979
    },
    {
      "name": "Rough Hood",
      "price": 9855,
      "": -55.006553296252605
    },
    {
      "name": "Reptile Hood",
      "price": 48174,
      "": 15825.669921331486
    },
    {
      "name": "Gobo Hood",
      "price": 100459,
      "": 4540.908036626119
    },
    {
      "name": "Beast Hood",
      "price": 203563,
      "": 1436.155180847505
    },
    {
      "name": "Umbral Hood",
      "price": 566489,
      "": -136489.31203468854
    },
    {
      "name": "Cotton Hat",
      "price": 6596,
      "": -1196.2718594187018
    },
    {
      "name": "Linen Hat",
      "price": 15768,
      "": -768.0239562195293
    },
    {
      "name": "Bamboo Hat",
      "price": 36370,
      "": 1629.3570162179603
    },
    {
      "name": "Silk Hat",
      "price": 220943,
      "": 9056.236813500553
    },
    {
      "name": "Radiant Hat",
      "price": 665337,
      "": -165337.59774897434
    },
    {
      "name": "Rough Tunic",
      "price": 15302,
      "": 197.66885524421923
    },
    {
      "name": "Reptile Tunic",
      "price": 75391,
      "": 8608.883053349433
    },
    {
      "name": "Gobo Tunic",
      "price": 156297,
      "": -1297.926103942329
    },
    {
      "name": "Beast Tunic",
      "price": 315065,
      "": 14934.158712525212
    },
    {
      "name": "Umbral Tunic",
      "price": 883847,
      "": -23847.025657496066
    },
    {
      "name": "Cotton Robe Top",
      "price": 10088,
      "": -1288.355634551699
    },
    {
      "name": "Linen Robe Top",
      "price": 23541,
      "": 458.9728492678005
    },
    {
      "name": "Bamboo Robe Top",
      "price": 53756,
      "": -1756.4077365954
    },
    {
      "name": "Silk Robe Top",
      "price": 342873,
      "": -2873.7106752298423
    },
    {
      "name": "Radiant Robe Top",
      "price": 1042004,
      "": -122004.28280035313
    },
    {
      "name": "Rough Chaps",
      "price": 13483,
      "": 16.20697323391687
    },
    {
      "name": "Reptile Chaps",
      "price": 66308,
      "": 1691.5687030113186
    },
    {
      "name": "Gobo Chaps",
      "price": 137655,
      "": 12344.068616380013
    },
    {
      "name": "Beast Chaps",
      "price": 277823,
      "": 7176.2587268839125
    },
    {
      "name": "Umbral Chaps",
      "price": 777890,
      "": 22109.885023854324
    },
    {
      "name": "Cotton Robe Bottoms",
      "price": 8921,
      "": -1121.5644553375132
    },
    {
      "name": "Linen Robe Bottoms",
      "price": 20939,
      "": 560.3972744398961
    },
    {
      "name": "Bamboo Robe Bottoms",
      "price": 47932,
      "": -1932.102812191406
    },
    {
      "name": "Silk Robe Bottoms",
      "price": 302155,
      "": 7844.3730125981965
    },
    {
      "name": "Radiant Robe Bottoms",
      "price": 916277,
      "": -36277.71497614565
    },
    {
      "name": "Rough Bracers",
      "price": 8036,
      "": 563.2166151952051
    },
    {
      "name": "Reptile Bracers",
      "price": 39092,
      "": 5907.124026816098
    },
    {
      "name": "Gobo Bracers",
      "price": 81820,
      "": 4179.283738812126
    },
    {
      "name": "Beast Bracers",
      "price": 166331,
      "": 3668.3272615435126
    },
    {
      "name": "Umbral Bracers",
      "price": 460556,
      "": -556.7118409965187
    },
    {
      "name": "Cotton Gloves",
      "price": 5429,
      "": -429.795629702754
    },
    {
      "name": "Linen Gloves",
      "price": 13167,
      "": 832.1689247752838
    },
    {
      "name": "Bamboo Gloves",
      "price": 30549,
      "": -1049.9570775144057
    },
    {
      "name": "Silk Gloves",
      "price": 180235,
      "": -235.60743233404355
    },
    {
      "name": "Radiant Gloves",
      "price": 539635,
      "": -159635.3404124251
    },
    {
      "name": "Rough Boots",
      "price": 8031,
      "": 168.3426513719951
    },
    {
      "name": "Reptile Boots",
      "price": 39066,
      "": 4933.4108985600105
    },
    {
      "name": "Gobo Boots",
      "price": 81743,
      "": 33256.71384317368
    },
    {
      "name": "Beast Boots",
      "price": 166129,
      "": 8870.401879829995
    },
    {
      "name": "Umbral Boots",
      "price": 460094,
      "": -20094.418908916938
    },
    {
      "name": "Cotton Boots",
      "price": 5424,
      "": -224.66959352596405
    },
    {
      "name": "Linen Boots",
      "price": 13141,
      "": 858.4557965191889
    },
    {
      "name": "Bamboo Boots",
      "price": 30472,
      "": 2527.473026847143
    },
    {
      "name": "Silk Boots",
      "price": 180033,
      "": -33.532814047532156
    },
    {
      "name": "Radiant Boots",
      "price": 539173,
      "": -19173.047480345587
    },
    {
      "name": "Wooden Crossbow",
      "price": 5000,
      "": 0
    },
    {
      "name": "Birch Crossbow",
      "price": 29801,
      "": 2198.8163162687415
    },
    {
      "name": "Cedar Crossbow",
      "price": 85814,
      "": 10185.521715545896
    },
    {
      "name": "Purpleheart Crossbow",
      "price": 202233,
      "": -17233.504331928096
    },
    {
      "name": "Ginkgo Crossbow",
      "price": 429234,
      "": 10765.349468893546
    },
    {
      "name": "Redwood Crossbow",
      "price": 781082,
      "": 18917.271064463886
    },
    {
      "name": "Arcane Crossbow",
      "price": 1362174,
      "": 37825.306008123094
    },
    {
      "name": "Wooden Water Staff",
      "price": 5000,
      "": 0
    },
    {
      "name": "Birch Water Staff",
      "price": 29801,
      "": 2198.8163162687415
    },
    {
      "name": "Cedar Water Staff",
      "price": 85814,
      "": 2185.521715545896
    },
    {
      "name": "Purpleheart Water Staff",
      "price": 202233,
      "": 22766.495668071904
    },
    {
      "name": "Ginkgo Water Staff",
      "price": 429234,
      "": 10765.349468893546
    },
    {
      "name": "Redwood Water Staff",
      "price": 781082,
      "": 38917.27106446389
    },
    {
      "name": "Arcane Water Staff",
      "price": 1362174,
      "": 37825.306008123094
    },
    {
      "name": "Wooden Nature Staff",
      "price": 5000,
      "": 0
    },
    {
      "name": "Birch Nature Staff",
      "price": 29820,
      "": 1179.367766840045
    },
    {
      "name": "Cedar Nature Staff",
      "price": 85857,
      "": 8142.7158373105485
    },
    {
      "name": "Purpleheart Nature Staff",
      "price": 202320,
      "": -7320.14726669286
    },
    {
      "name": "Ginkgo Nature Staff",
      "price": 429403,
      "": 596.962175829045
    },
    {
      "name": "Redwood Nature Staff",
      "price": 781410,
      "": 18589.292377206497
    },
    {
      "name": "Arcane Nature Staff",
      "price": 1362816,
      "": 37183.863435438834
    },
    {
      "name": "Wooden Fire Staff",
      "price": 5000,
      "": 0
    },
    {
      "name": "Birch Fire Staff",
      "price": 29843,
      "": 156.9391798092438
    },
    {
      "name": "Cedar Fire Staff",
      "price": 85903,
      "": 6096.4386019777885
    },
    {
      "name": "Purpleheart Fire Staff",
      "price": 202411,
      "": -2411.234850218636
    },
    {
      "name": "Ginkgo Fire Staff",
      "price": 429577,
      "": 10422.208645891107
    },
    {
      "name": "Redwood Fire Staff",
      "price": 781749,
      "": 18250.961654019775
    },
    {
      "name": "Arcane Fire Staff",
      "price": 1363476,
      "": 36523.71869668574
    },
    {
      "name": "Wooden Bow",
      "price": 5000,
      "": 0
    },
    {
      "name": "Birch Bow",
      "price": 37330,
      "": 669.3754791871615
    },
    {
      "name": "Cedar Bow",
      "price": 111306,
      "": 28693.839179107046
    },
    {
      "name": "Purpleheart Bow",
      "price": 265274,
      "": 29725.763667070365
    },
    {
      "name": "Ginkgo Bow",
      "price": 565734,
      "": 34265.78287573671
    },
    {
      "name": "Redwood Bow",
      "price": 1030819,
      "": 19180.044272716972
    },
    {
      "name": "Arcane Bow",
      "price": 1798186,
      "": -98186.8566002755
    },
    {
      "name": "Wooden Shield",
      "price": 5572,
      "": -672.0569765560376
    },
    {
      "name": "Birch Shield",
      "price": 21995,
      "": 4004.3982139988984
    },
    {
      "name": "Cedar Shield",
      "price": 60622,
      "": 1377.3614070388358
    },
    {
      "name": "Purpleheart Shield",
      "price": 140685,
      "": -685.252166380902
    },
    {
      "name": "Ginkgo Shield",
      "price": 296551,
      "": -81551.60275637818
    },
    {
      "name": "Redwood Shield",
      "price": 538821,
      "": 21178.278557332116
    },
    {
      "name": "Arcane Shield",
      "price": 939776,
      "": -199776.0773500125
    }
  ],
  "time": 1781539061.736
}