{
  "train": [
    {
      "name": "Cheese Brush",
      "price": 5000,
      "": 0
    },
    {
      "name": "Verdant Brush",
      "price": 28293,
      "": 206.55810485571783
    },
    {
      "name": "Azure Brush",
      "price": 71758,
      "": 4241.034438370494
    },
    {
      "name": "Burble Brush",
      "price": 158337,
      "": 1662.9448106339842
    },
    {
      "name": "Crimson Brush",
      "price": 331137,
      "": 18862.482989316864
    },
    {
      "name": "Rainbow Brush",
      "price": 626612,
      "": 13387.730720291846
    },
    {
      "name": "Holy Brush",
      "price": 1207270,
      "": -7270.601457735989
    },
    {
      "name": "Cheese Shears",
      "price": 5000,
      "": 0
    },
    {
      "name": "Verdant Shears",
      "price": 28293,
      "": 206.55810485571783
    },
    {
      "name": "Azure Shears",
      "price": 71758,
      "": 4241.034438370494
    },
    {
      "name": "Burble Shears",
      "price": 158337,
      "": 6662.944810633984
    },
    {
      "name": "Crimson Shears",
      "price": 331137,
      "": 18862.482989316864
    },
    {
      "name": "Rainbow Shears",
      "price": 626612,
      "": 13387.730720291846
    },
    {
      "name": "Holy Shears",
      "price": 1207270,
      "": -7270.601457735989
    },
    {
      "name": "Cheese Hatchet",
      "price": 5000,
      "": 0
    },
    {
      "name": "Verdant Hatchet",
      "price": 28293,
      "": -793.4418951442822
    },
    {
      "name": "Azure Hatchet",
      "price": 71758,
      "": 4241.034438370494
    },
    {
      "name": "Burble Hatchet",
      "price": 158337,
      "": 6662.944810633984
    },
    {
      "name": "Crimson Hatchet",
      "price": 331137,
      "": 18862.482989316864
    },
    {
      "name": "Rainbow Hatchet",
      "price": 626612,
      "": -6612.2692797081545
    },
    {
      "name": "Holy Hatchet",
      "price": 1207270,
      "": -7270.601457735989
    },
    {
      "name": "Cheese Hammer",
      "price": 5000,
      "": 0
    },
    {
      "name": "Verdant Hammer",
      "price": 28308,
      "": 191.74807243166651
    },
    {
      "name": "Azure Hammer",
      "price": 71789,
      "": 2210.4840225000953
    },
    {
      "name": "Burble Hammer",
      "price": 158397,
      "": 6602.83608310594
    },
    {
      "name": "Crimson Hammer",
      "price": 331252,
      "": 18747.221076921443
    },
    {
      "name": "Rainbow Hammer",
      "price": 626835,
      "": -6835.284484702977
    },
    {
      "name": "Holy Hammer",
      "price": 1207705,
      "": 42294.5681069952
    },
    {
      "name": "Cheese Chisel",
      "price": 5000,
      "": 0
    },
    {
      "name": "Verdant Chisel",
      "price": 28308,
      "": 691.7480724316665
    },
    {
      "name": "Azure Chisel",
      "price": 71789,
      "": 4210.484022500095
    },
    {
      "name": "Burble Chisel",
      "price": 158397,
      "": 6602.83608310594
    },
    {
      "name": "Crimson Chisel",
      "price": 331252,
      "": 18747.221076921443
    },
    {
      "name": "Rainbow Chisel",
      "price": 626835,
      "": 13164.715515297023
    },
    {
      "name": "Holy Chisel",
      "price": 1207705,
      "": -7705.431893004803
    },
    {
      "name": "Cheese Spatula",
      "price": 5000,
      "": 0
    },
    {
      "name": "Verdant Spatula",
      "price": 30154,
      "": 845.1317459010534
    },
    {
      "name": "Azure Spatula",
      "price": 74251,
      "": 3748.328920459273
    },
    {
      "name": "Burble Spatula",
      "price": 161945,
      "": 8054.436083105975
    },
    {
      "name": "Crimson Spatula",
      "price": 337326,
      "": 2673.301689166343
    },
    {
      "name": "Rainbow Spatula",
      "price": 647030,
      "": -7030.3875459276605
    },
    {
      "name": "Holy Spatula",
      "price": 1264398,
      "": -114398.36352565815
    },
    {
      "name": "Cheese Needle",
      "price": 5000,
      "": 0
    },
    {
      "name": "Verdant Needle",
      "price": 30154,
      "": 845.1317459010534
    },
    {
      "name": "Azure Needle",
      "price": 74251,
      "": 3748.328920459273
    },
    {
      "name": "Burble Needle",
      "price": 161945,
      "": 8054.436083105975
    },
    {
      "name": "Crimson Needle",
      "price": 337326,
      "": 22673.301689166343
    },
    {
      "name": "Rainbow Needle",
      "price": 647030,
      "": 32969.61245407234
    },
    {
      "name": "Holy Needle",
      "price": 1264398,
      "": 35601.63647434185
    },
    {
      "name": "Cheese Pot",
      "price": 5000,
      "": 0
    },
    {
      "name": "Verdant Pot",
      "price": 30154,
      "": 845.1317459010534
    },
    {
      "name": "Azure Pot",
      "price": 74251,
      "": 3748.328920459273
    },
    {
      "name": "Burble Pot",
      "price": 161945,
      "": 8054.436083105975
    },
    {
      "name": "Crimson Pot",
      "price": 337326,
      "": -7326.698310833657
    },
    {
      "name": "Rainbow Pot",
      "price": 647030,
      "": -7030.3875459276605
    },
    {
      "name": "Holy Pot",
      "price": 1264398,
      "": -14398.363525658147
    },
    {
      "name": "Cheese Alembic",
      "price": 5000,
      "": 0
    },
    {
      "name": "Verdant Alembic",
      "price": 30169,
      "": 830.123353691295
    },
    {
      "name": "Azure Alembic",
      "price": 74282,
      "": 3717.3594130201527
    },
    {
      "name": "Burble Alembic",
      "price": 162006,
      "": -2006.529248004721
    },
    {
      "name": "Crimson Alembic",
      "price": 337443,
      "": 2556.3188386816764
    },
    {
      "name": "Rainbow Alembic",
      "price": 647256,
      "": -7256.917783127516
    },
    {
      "name": "Holy Alembic",
      "price": 1264840,
      "": 35159.529415138764
    },
    {
      "name": "Cheese Enhancer",
      "price": 5000,
      "": 0
    },
    {
      "name": "Verdant Enhancer",
      "price": 30169,
      "": 830.123353691295
    },
    {
      "name": "Azure Enhancer",
      "price": 74282,
      "": 1717.3594130201527
    },
    {
      "name": "Burble Enhancer",
      "price": 162006,
      "": -2006.529248004721
    },
    {
      "name": "Crimson Enhancer",
      "price": 337443,
      "": 2556.3188386816764
    },
    {
      "name": "Rainbow Enhancer",
      "price": 647256,
      "": 12743.082216872484
    },
    {
      "name": "Holy Enhancer",
      "price": 1264840,
      "": 35159.529415138764
    },
    {
      "name": "Cheese Bulwark",
      "price": 15144,
      "": -6144.374188595777
    },
    {
      "name": "Verdant Bulwark",
      "price": 55707,
      "": -19707.521783306474
    },
    {
      "name": "Azure Bulwark",
      "price": 129700,
      "": -37700.08520595412
    },
    {
      "name": "Burble Bulwark",
      "price": 277182,
      "": -112182.60828042927
    },
    {
      "name": "Crimson Bulwark",
      "price": 572813,
      "": -102813.9412900036
    },
    {
      "name": "Rainbow Bulwark",
      "price": 1094500,
      "": -314500.3935533911
    },
    {
      "name": "Holy Bulwark",
      "price": 2135828,
      "": -435828.6870199451
    },
    {
      "name": "Cheese Sword",
      "price": 5000,
      "": 0
    },
    {
      "name": "Verdant Sword",
      "price": 36650,
      "": 1349.804247004664
    },
    {
      "name": "Azure Sword",
      "price": 92672,
      "": 1327.836770727823
    },
    {
      "name": "Burble Sword",
      "price": 204219,
      "": 780.7325591890258
    },
    {
      "name": "Crimson Sword",
      "price": 427584,
      "": 12415.67330984975
    },
    {
      "name": "Rainbow Sword",
      "price": 821854,
      "": 18145.852904420346
    },
    {
      "name": "Holy Sword",
      "price": 1608359,
      "": -8359.98427524534
    },
    {
      "name": "Cheese Spear",
      "price": 5000,
      "": 0
    },
    {
      "name": "Verdant Spear",
      "price": 32971,
      "": 28.324575738588464
    },
    {
      "name": "Azure Spear",
      "price": 87778,
      "": 2221.8029197903816
    },
    {
      "name": "Burble Spear",
      "price": 197182,
      "": 7817.845367633738
    },
    {
      "name": "Crimson Spear",
      "price": 415550,
      "": 4449.096393624903
    },
    {
      "name": "Rainbow Spear",
      "price": 781685,
      "": 18314.770606785663
    },
    {
      "name": "Holy Spear",
      "price": 1495405,
      "": -45405.38067794009
    },
    {
      "name": "Cheese Mace",
      "price": 5000,
      "": 0
    },
    {
      "name": "Verdant Mace",
      "price": 32986,
      "": 13.415858376429242
    },
    {
      "name": "Azure Mace",
      "price": 87808,
      "": 191.04402944059984
    },
    {
      "name": "Burble Mace",
      "price": 197242,
      "": 7757.310614947171
    },
    {
      "name": "Crimson Mace",
      "price": 415667,
      "": 14332.978808879328
    },
    {
      "name": "Rainbow Mace",
      "price": 781909,
      "": 18090.008237177855
    },
    {
      "name": "Holy Mace",
      "price": 1495843,
      "": 4156.173341594171
    },
    {
      "name": "Cheese Buckler",
      "price": 7972,
      "": -1772.5175084564162
    },
    {
      "name": "Verdant Buckler",
      "price": 28978,
      "": -478.3174626352411
    },
    {
      "name": "Azure Buckler",
      "price": 67116,
      "": 2883.2655354691233
    },
    {
      "name": "Burble Buckler",
      "price": 142891,
      "": -7891.929248004744
    },
    {
      "name": "Crimson Buckler",
      "price": 294295,
      "": -4295.9127939714235
    },
    {
      "name": "Rainbow Buckler",
      "price": 561745,
      "": -131745.5983953724
    },
    {
      "name": "Holy Buckler",
      "price": 1094602,
      "": -154602.04915628978
    },
    {
      "name": "Cheese Helmet",
      "price": 6777,
      "": -377.648120701313
    },
    {
      "name": "Verdant Helmet",
      "price": 24524,
      "": 1475.2866189974156
    },
    {
      "name": "Azure Helmet",
      "price": 56688,
      "": 1311.2165558772904
    },
    {
      "name": "Burble Helmet",
      "price": 120515,
      "": 4484.715649954465
    },
    {
      "name": "Crimson Helmet",
      "price": 247886,
      "": 7113.900471334724
    },
    {
      "name": "Rainbow Helmet",
      "price": 472972,
      "": 7027.765890341951
    },
    {
      "name": "Holy Helmet",
      "price": 921101,
      "": -41101.58282975899
    },
    {
      "name": "Cheese Plate Body",
      "price": 10370,
      "": -370.2297604944688
    },
    {
      "name": "Verdant Plate Body",
      "price": 37908,
      "": 2091.581053016649
    },
    {
      "name": "Azure Plate Body",
      "price": 88019,
      "": 1980.1043639479321
    },
    {
      "name": "Burble Plate Body",
      "price": 187738,
      "": 2261.6862672426505
    },
    {
      "name": "Crimson Plate Body",
      "price": 387294,
      "": 22705.674105731887
    },
    {
      "name": "Rainbow Plate Body",
      "price": 739638,
      "": 20361.102201008936
    },
    {
      "name": "Holy Plate Body",
      "price": 1442280,
      "": 57719.80698972219
    },
    {
      "name": "Cheese Plate Legs",
      "price": 9172,
      "": -172.6850177121487
    },
    {
      "name": "Verdant Plate Legs",
      "price": 33447,
      "": 1552.8676907250483
    },
    {
      "name": "Azure Plate Legs",
      "price": 77576,
      "": 2423.917227181126
    },
    {
      "name": "Burble Plate Legs",
      "price": 165330,
      "": 4669.585444189608
    },
    {
      "name": "Crimson Plate Legs",
      "price": 340824,
      "": 19175.531198370154
    },
    {
      "name": "Rainbow Plate Legs",
      "price": 650749,
      "": 9250.907912029768
    },
    {
      "name": "Holy Plate Legs",
      "price": 1268552,
      "": -18552.084403375397
    },
    {
      "name": "Cheese Gauntlets",
      "price": 5569,
      "": -169.8322853262107
    },
    {
      "name": "Verdant Gauntlets",
      "price": 20033,
      "": 966.0409816985339
    },
    {
      "name": "Azure Gauntlets",
      "price": 46184,
      "": 2815.808199299252
    },
    {
      "name": "Burble Gauntlets",
      "price": 97987,
      "": 7012.173375515587
    },
    {
      "name": "Crimson Gauntlets",
      "price": 201187,
      "": 13812.955962911015
    },
    {
      "name": "Rainbow Gauntlets",
      "price": 383639,
      "": 6360.89065952244
    },
    {
      "name": "Holy Gauntlets",
      "price": 746509,
      "": -66509.4363160613
    },
    {
      "name": "Cheese Boots",
      "price": 5569,
      "": -169.8322853262107
    },
    {
      "name": "Verdant Boots",
      "price": 20029,
      "": -529.2146684227446
    },
    {
      "name": "Azure Boots",
      "price": 46171,
      "": 2828.2879049920666
    },
    {
      "name": "Burble Boots",
      "price": 97960,
      "": 7039.165314460581
    },
    {
      "name": "Crimson Boots",
      "price": 201133,
      "": -1133.0020907055587
    },
    {
      "name": "Rainbow Boots",
      "price": 383532,
      "": 26467.71794225159
    },
    {
      "name": "Holy Boots",
      "price": 746298,
      "": -6298.985443934565
    },
    {
      "name": "Rough Hood",
      "price": 9493,
      "": 106.73963440072657
    },
    {
      "name": "Reptile Hood",
      "price": 47813,
      "": -813.4658439965642
    },
    {
      "name": "Gobo Hood",
      "price": 101684,
      "": -1684.3240437636705
    },
    {
      "name": "Beast Hood",
      "price": 207509,
      "": -22509.190037192573
    },
    {
      "name": "Umbral Hood",
      "price": 562296,
      "": -172296.492463651
    },
    {
      "name": "Cotton Hat",
      "price": 6596,
      "": -996.607304374782
    },
    {
      "name": "Linen Hat",
      "price": 18484,
      "": 1015.146400901398
    },
    {
      "name": "Bamboo Hat",
      "price": 42257,
      "": -3257.6760845799945
    },
    {
      "name": "Silk Hat",
      "price": 232266,
      "": 2733.4783301544376
    },
    {
      "name": "Radiant Hat",
      "price": 652228,
      "": -112228.5179738549
    },
    {
      "name": "Rough Tunic",
      "price": 14723,
      "": 776.6572965948708
    },
    {
      "name": "Reptile Tunic",
      "price": 74813,
      "": -6813.029075402577
    },
    {
      "name": "Gobo Tunic",
      "price": 158256,
      "": 1743.5559991316986
    },
    {
      "name": "Beast Tunic",
      "price": 321373,
      "": -1373.9502379240585
    },
    {
      "name": "Umbral Tunic",
      "price": 877129,
      "": 2870.900186300627
    },
    {
      "name": "Cotton Robe Top",
      "price": 10088,
      "": 911.3021945540568
    },
    {
      "name": "Linen Robe Top",
      "price": 27887,
      "": 1112.750516434142
    },
    {
      "name": "Bamboo Robe Top",
      "price": 63173,
      "": -7173.80726617443
    },
    {
      "name": "Silk Robe Top",
      "price": 360985,
      "": -20985.68085016904
    },
    {
      "name": "Radiant Robe Top",
      "price": 1021020,
      "": -81020.34063002607
    },
    {
      "name": "Rough Chaps",
      "price": 12977,
      "": -977.2175155965087
    },
    {
      "name": "Reptile Chaps",
      "price": 65802,
      "": 2197.2530498375418
    },
    {
      "name": "Gobo Chaps",
      "price": 139370,
      "": 10629.99146082424
    },
    {
      "name": "Beast Chaps",
      "price": 283344,
      "": -3344.2310779290274
    },
    {
      "name": "Umbral Chaps",
      "price": 772013,
      "": 7986.18021582847
    },
    {
      "name": "Cotton Robe Bottoms",
      "price": 8921,
      "": 1578.0967701177742
    },
    {
      "name": "Linen Robe Bottoms",
      "price": 24742,
      "": 757.3101926946838
    },
    {
      "name": "Bamboo Robe Bottoms",
      "price": 56172,
      "": 3827.2986036813672
    },
    {
      "name": "Silk Robe Bottoms",
      "price": 318004,
      "": 1995.5046363566653
    },
    {
      "name": "Radiant Robe Bottoms",
      "price": 897918,
      "": -17918.655498457374
    },
    {
      "name": "Rough Bracers",
      "price": 7747,
      "": 452.54974113859225
    },
    {
      "name": "Reptile Bracers",
      "price": 38804,
      "": 195.58422257948405
    },
    {
      "name": "Gobo Bracers",
      "price": 82801,
      "": 3198.4908879205614
    },
    {
      "name": "Beast Bracers",
      "price": 169489,
      "": 5510.597041671106
    },
    {
      "name": "Umbral Bracers",
      "price": 457205,
      "": 12794.466922329972
    },
    {
      "name": "Cotton Gloves",
      "price": 5430,
      "": -530.1278098818166
    },
    {
      "name": "Linen Gloves",
      "price": 15341,
      "": 2158.474018497849
    },
    {
      "name": "Bamboo Gloves",
      "price": 35260,
      "": 1739.8092552675007
    },
    {
      "name": "Silk Gloves",
      "price": 189295,
      "": 5704.731735548616
    },
    {
      "name": "Radiant Gloves",
      "price": 529151,
      "": -149151.15348583332
    },
    {
      "name": "Rough Boots",
      "price": 7742,
      "": 657.6779187554221
    },
    {
      "name": "Reptile Boots",
      "price": 38778,
      "": 3221.882075861118
    },
    {
      "name": "Gobo Boots",
      "price": 82724,
      "": 7275.953339288666
    },
    {
      "name": "Beast Boots",
      "price": 169287,
      "": 20712.756078144273
    },
    {
      "name": "Umbral Boots",
      "price": 456743,
      "": 3256.9529807475046
    },
    {
      "name": "Cotton Boots",
      "price": 5424,
      "": -424.99963226498676
    },
    {
      "name": "Linen Boots",
      "price": 15315,
      "": 3184.771871779487
    },
    {
      "name": "Bamboo Boots",
      "price": 35182,
      "": 2817.271706635598
    },
    {
      "name": "Silk Boots",
      "price": 189093,
      "": -4093.109227978217
    },
    {
      "name": "Radiant Boots",
      "price": 528688,
      "": 51311.33257258427
    },
    {
      "name": "Wooden Crossbow",
      "price": 5000,
      "": 0
    },
    {
      "name": "Birch Crossbow",
      "price": 29802,
      "": 2197.8914540262376
    },
    {
      "name": "Cedar Crossbow",
      "price": 89075,
      "": 2924.924639685938
    },
    {
      "name": "Purpleheart Crossbow",
      "price": 203051,
      "": 6948.28164099119
    },
    {
      "name": "Ginkgo Crossbow",
      "price": 430055,
      "": 29944.1958684781
    },
    {
      "name": "Redwood Crossbow",
      "price": 771318,
      "": 28681.599574904656
    },
    {
      "name": "Arcane Crossbow",
      "price": 1352420,
      "": 47579.67169892276
    },
    {
      "name": "Wooden Water Staff",
      "price": 5000,
      "": 0
    },
    {
      "name": "Birch Water Staff",
      "price": 29802,
      "": 3197.8914540262376
    },
    {
      "name": "Cedar Water Staff",
      "price": 89075,
      "": 4924.924639685938
    },
    {
      "name": "Purpleheart Water Staff",
      "price": 203051,
      "": 26948.28164099119
    },
    {
      "name": "Ginkgo Water Staff",
      "price": 430055,
      "": 59944.1958684781
    },
    {
      "name": "Redwood Water Staff",
      "price": 771318,
      "": 28681.599574904656
    },
    {
      "name": "Arcane Water Staff",
      "price": 1352420,
      "": 47579.67169892276
    },
    {
      "name": "Wooden Nature Staff",
      "price": 5000,
      "": 0
    },
    {
      "name": "Birch Nature Staff",
      "price": 29821,
      "": 3178.4347798202216
    },
    {
      "name": "Cedar Nature Staff",
      "price": 89117,
      "": 50882.10087897406
    },
    {
      "name": "Purpleheart Nature Staff",
      "price": 203138,
      "": 31861.60251049089
    },
    {
      "name": "Ginkgo Nature Staff",
      "price": 430224,
      "": 29775.738230359566
    },
    {
      "name": "Redwood Nature Staff",
      "price": 771646,
      "": 8353.483872091863
    },
    {
      "name": "Arcane Nature Staff",
      "price": 1353062,
      "": 46937.96115879482
    },
    {
      "name": "Wooden Fire Staff",
      "price": 5000,
      "": 0
    },
    {
      "name": "Birch Fire Staff",
      "price": 29844,
      "": 3155.996823079051
    },
    {
      "name": "Cedar Fire Staff",
      "price": 89164,
      "": 6835.804310979336
    },
    {
      "name": "Purpleheart Fire Staff",
      "price": 203229,
      "": 11770.476874444284
    },
    {
      "name": "Ginkgo Fire Staff",
      "price": 430399,
      "": 29600.91169582453
    },
    {
      "name": "Redwood Fire Staff",
      "price": 771984,
      "": 8015.011808709358
    },
    {
      "name": "Arcane Fire Staff",
      "price": 1353722,
      "": 46277.540639628656
    },
    {
      "name": "Wooden Bow",
      "price": 5000,
      "": 0
    },
    {
      "name": "Birch Bow",
      "price": 37331,
      "": 3668.436266539691
    },
    {
      "name": "Cedar Bow",
      "price": 115653,
      "": 24346.96647842019
    },
    {
      "name": "Purpleheart Bow",
      "price": 266364,
      "": 13635.926941477752
    },
    {
      "name": "Ginkgo Bow",
      "price": 566827,
      "": 33172.94921704254
    },
    {
      "name": "Redwood Bow",
      "price": 1017797,
      "": -17797.123395475443
    },
    {
      "name": "Arcane Bow",
      "price": 1785174,
      "": -185174.2072706509
    },
    {
      "name": "Wooden Shield",
      "price": 5789,
      "": 4210.362937855508
    },
    {
      "name": "Birch Shield",
      "price": 22213,
      "": 2786.219329345513
    },
    {
      "name": "Cedar Shield",
      "price": 63045,
      "": -9045.843112649898
    },
    {
      "name": "Purpleheart Shield",
      "price": 141457,
      "": -6457.07559752927
    },
    {
      "name": "Ginkgo Shield",
      "price": 297326,
      "": -97326.38843925454
    },
    {
      "name": "Redwood Shield",
      "price": 532438,
      "": -202438.69172868785
    },
    {
      "name": "Arcane Shield",
      "price": 933403,
      "": -213403.0973761034
    }
  ],
  "time": 1780418560.662
}