{
  "train": [
    {
      "name": "Cheese Brush",
      "price": 5468,
      "hrid": "/items/cheese_brush"
    },
    {
      "name": "Verdant Brush",
      "price": 18923,
      "hrid": "/items/verdant_brush"
    },
    {
      "name": "Azure Brush",
      "price": 46224,
      "hrid": "/items/azure_brush"
    },
    {
      "name": "Burble Brush",
      "price": 99310,
      "hrid": "/items/burble_brush"
    },
    {
      "name": "Crimson Brush",
      "price": 173754,
      "hrid": "/items/crimson_brush"
    },
    {
      "name": "Rainbow Brush",
      "price": 330864,
      "hrid": "/items/rainbow_brush"
    },
    {
      "name": "Holy Brush",
      "price": 611074,
      "hrid": "/items/holy_brush"
    },
    {
      "name": "Cheese Shears",
      "price": 5468,
      "hrid": "/items/cheese_shears"
    },
    {
      "name": "Verdant Shears",
      "price": 18923,
      "hrid": "/items/verdant_shears"
    },
    {
      "name": "Azure Shears",
      "price": 46224,
      "hrid": "/items/azure_shears"
    },
    {
      "name": "Burble Shears",
      "price": 99310,
      "hrid": "/items/burble_shears"
    },
    {
      "name": "Crimson Shears",
      "price": 173754,
      "hrid": "/items/crimson_shears"
    },
    {
      "name": "Rainbow Shears",
      "price": 330864,
      "hrid": "/items/rainbow_shears"
    },
    {
      "name": "Holy Shears",
      "price": 611074,
      "hrid": "/items/holy_shears"
    },
    {
      "name": "Cheese Hatchet",
      "price": 5468,
      "hrid": "/items/cheese_hatchet"
    },
    {
      "name": "Verdant Hatchet",
      "price": 18923,
      "hrid": "/items/verdant_hatchet"
    },
    {
      "name": "Azure Hatchet",
      "price": 46224,
      "hrid": "/items/azure_hatchet"
    },
    {
      "name": "Burble Hatchet",
      "price": 99310,
      "hrid": "/items/burble_hatchet"
    },
    {
      "name": "Crimson Hatchet",
      "price": 173754,
      "hrid": "/items/crimson_hatchet"
    },
    {
      "name": "Rainbow Hatchet",
      "price": 330864,
      "hrid": "/items/rainbow_hatchet"
    },
    {
      "name": "Holy Hatchet",
      "price": 611074,
      "hrid": "/items/holy_hatchet"
    },
    {
      "name": "Cheese Hammer",
      "price": 5472,
      "hrid": "/items/cheese_hammer"
    },
    {
      "name": "Verdant Hammer",
      "price": 18933,
      "hrid": "/items/verdant_hammer"
    },
    {
      "name": "Azure Hammer",
      "price": 46244,
      "hrid": "/items/azure_hammer"
    },
    {
      "name": "Burble Hammer",
      "price": 99351,
      "hrid": "/items/burble_hammer"
    },
    {
      "name": "Crimson Hammer",
      "price": 173835,
      "hrid": "/items/crimson_hammer"
    },
    {
      "name": "Rainbow Hammer",
      "price": 331029,
      "hrid": "/items/rainbow_hammer"
    },
    {
      "name": "Holy Hammer",
      "price": 611414,
      "hrid": "/items/holy_hammer"
    },
    {
      "name": "Cheese Chisel",
      "price": 5472,
      "hrid": "/items/cheese_chisel"
    },
    {
      "name": "Verdant Chisel",
      "price": 18933,
      "hrid": "/items/verdant_chisel"
    },
    {
      "name": "Azure Chisel",
      "price": 46244,
      "hrid": "/items/azure_chisel"
    },
    {
      "name": "Burble Chisel",
      "price": 99351,
      "hrid": "/items/burble_chisel"
    },
    {
      "name": "Crimson Chisel",
      "price": 173835,
      "hrid": "/items/crimson_chisel"
    },
    {
      "name": "Rainbow Chisel",
      "price": 331029,
      "hrid": "/items/rainbow_chisel"
    },
    {
      "name": "Holy Chisel",
      "price": 611414,
      "hrid": "/items/holy_chisel"
    },
    {
      "name": "Cheese Spatula",
      "price": 5472,
      "hrid": "/items/cheese_spatula"
    },
    {
      "name": "Verdant Spatula",
      "price": 19263,
      "hrid": "/items/verdant_spatula"
    },
    {
      "name": "Azure Spatula",
      "price": 47346,
      "hrid": "/items/azure_spatula"
    },
    {
      "name": "Burble Spatula",
      "price": 101389,
      "hrid": "/items/burble_spatula"
    },
    {
      "name": "Crimson Spatula",
      "price": 180172,
      "hrid": "/items/crimson_spatula"
    },
    {
      "name": "Rainbow Spatula",
      "price": 345722,
      "hrid": "/items/rainbow_spatula"
    },
    {
      "name": "Holy Spatula",
      "price": 630572,
      "hrid": "/items/holy_spatula"
    },
    {
      "name": "Cheese Needle",
      "price": 5472,
      "hrid": "/items/cheese_needle"
    },
    {
      "name": "Verdant Needle",
      "price": 19263,
      "hrid": "/items/verdant_needle"
    },
    {
      "name": "Azure Needle",
      "price": 47346,
      "hrid": "/items/azure_needle"
    },
    {
      "name": "Burble Needle",
      "price": 101389,
      "hrid": "/items/burble_needle"
    },
    {
      "name": "Crimson Needle",
      "price": 180172,
      "hrid": "/items/crimson_needle"
    },
    {
      "name": "Rainbow Needle",
      "price": 345722,
      "hrid": "/items/rainbow_needle"
    },
    {
      "name": "Holy Needle",
      "price": 630572,
      "hrid": "/items/holy_needle"
    },
    {
      "name": "Cheese Pot",
      "price": 5472,
      "hrid": "/items/cheese_pot"
    },
    {
      "name": "Verdant Pot",
      "price": 19263,
      "hrid": "/items/verdant_pot"
    },
    {
      "name": "Azure Pot",
      "price": 47346,
      "hrid": "/items/azure_pot"
    },
    {
      "name": "Burble Pot",
      "price": 101389,
      "hrid": "/items/burble_pot"
    },
    {
      "name": "Crimson Pot",
      "price": 180172,
      "hrid": "/items/crimson_pot"
    },
    {
      "name": "Rainbow Pot",
      "price": 345722,
      "hrid": "/items/rainbow_pot"
    },
    {
      "name": "Holy Pot",
      "price": 630572,
      "hrid": "/items/holy_pot"
    },
    {
      "name": "Cheese Alembic",
      "price": 5475,
      "hrid": "/items/cheese_alembic"
    },
    {
      "name": "Verdant Alembic",
      "price": 19273,
      "hrid": "/items/verdant_alembic"
    },
    {
      "name": "Azure Alembic",
      "price": 47367,
      "hrid": "/items/azure_alembic"
    },
    {
      "name": "Burble Alembic",
      "price": 101431,
      "hrid": "/items/burble_alembic"
    },
    {
      "name": "Crimson Alembic",
      "price": 180255,
      "hrid": "/items/crimson_alembic"
    },
    {
      "name": "Rainbow Alembic",
      "price": 345891,
      "hrid": "/items/rainbow_alembic"
    },
    {
      "name": "Holy Alembic",
      "price": 630921,
      "hrid": "/items/holy_alembic"
    },
    {
      "name": "Cheese Enhancer",
      "price": 5475,
      "hrid": "/items/cheese_enhancer"
    },
    {
      "name": "Verdant Enhancer",
      "price": 19273,
      "hrid": "/items/verdant_enhancer"
    },
    {
      "name": "Azure Enhancer",
      "price": 47367,
      "hrid": "/items/azure_enhancer"
    },
    {
      "name": "Burble Enhancer",
      "price": 101431,
      "hrid": "/items/burble_enhancer"
    },
    {
      "name": "Crimson Enhancer",
      "price": 180255,
      "hrid": "/items/crimson_enhancer"
    },
    {
      "name": "Rainbow Enhancer",
      "price": 345891,
      "hrid": "/items/rainbow_enhancer"
    },
    {
      "name": "Holy Enhancer",
      "price": 630921,
      "hrid": "/items/holy_enhancer"
    },
    {
      "name": "Cheese Bulwark",
      "price": 11836,
      "hrid": "/items/cheese_bulwark"
    },
    {
      "name": "Verdant Bulwark",
      "price": 35005,
      "hrid": "/items/verdant_bulwark"
    },
    {
      "name": "Azure Bulwark",
      "price": 82389,
      "hrid": "/items/azure_bulwark"
    },
    {
      "name": "Burble Bulwark",
      "price": 173658,
      "hrid": "/items/burble_bulwark"
    },
    {
      "name": "Crimson Bulwark",
      "price": 306227,
      "hrid": "/items/crimson_bulwark"
    },
    {
      "name": "Rainbow Bulwark",
      "price": 585325,
      "hrid": "/items/rainbow_bulwark"
    },
    {
      "name": "Holy Bulwark",
      "price": 1064682,
      "hrid": "/items/holy_bulwark"
    },
    {
      "name": "Cheese Sword",
      "price": 5467,
      "hrid": "/items/cheese_sword"
    },
    {
      "name": "Verdant Sword",
      "price": 22996,
      "hrid": "/items/verdant_sword"
    },
    {
      "name": "Azure Sword",
      "price": 58778,
      "hrid": "/items/azure_sword"
    },
    {
      "name": "Burble Sword",
      "price": 127668,
      "hrid": "/items/burble_sword"
    },
    {
      "name": "Crimson Sword",
      "price": 227880,
      "hrid": "/items/crimson_sword"
    },
    {
      "name": "Rainbow Sword",
      "price": 438673,
      "hrid": "/items/rainbow_sword"
    },
    {
      "name": "Holy Sword",
      "price": 800954,
      "hrid": "/items/holy_sword"
    },
    {
      "name": "Cheese Spear",
      "price": 5470,
      "hrid": "/items/cheese_spear"
    },
    {
      "name": "Verdant Spear",
      "price": 22344,
      "hrid": "/items/verdant_spear"
    },
    {
      "name": "Azure Spear",
      "price": 56593,
      "hrid": "/items/azure_spear"
    },
    {
      "name": "Burble Spear",
      "price": 123630,
      "hrid": "/items/burble_spear"
    },
    {
      "name": "Crimson Spear",
      "price": 215286,
      "hrid": "/items/crimson_spear"
    },
    {
      "name": "Rainbow Spear",
      "price": 409448,
      "hrid": "/items/rainbow_spear"
    },
    {
      "name": "Holy Spear",
      "price": 762976,
      "hrid": "/items/holy_spear"
    },
    {
      "name": "Cheese Mace",
      "price": 5473,
      "hrid": "/items/cheese_mace"
    },
    {
      "name": "Verdant Mace",
      "price": 22354,
      "hrid": "/items/verdant_mace"
    },
    {
      "name": "Azure Mace",
      "price": 56614,
      "hrid": "/items/azure_mace"
    },
    {
      "name": "Burble Mace",
      "price": 123671,
      "hrid": "/items/burble_mace"
    },
    {
      "name": "Crimson Mace",
      "price": 215368,
      "hrid": "/items/crimson_mace"
    },
    {
      "name": "Rainbow Mace",
      "price": 409614,
      "hrid": "/items/rainbow_mace"
    },
    {
      "name": "Holy Mace",
      "price": 763321,
      "hrid": "/items/holy_mace"
    },
    {
      "name": "Cheese Buckler",
      "price": 6103,
      "hrid": "/items/cheese_buckler"
    },
    {
      "name": "Verdant Buckler",
      "price": 18028,
      "hrid": "/items/verdant_buckler"
    },
    {
      "name": "Azure Buckler",
      "price": 42265,
      "hrid": "/items/azure_buckler"
    },
    {
      "name": "Burble Buckler",
      "price": 88890,
      "hrid": "/items/burble_buckler"
    },
    {
      "name": "Crimson Buckler",
      "price": 156969,
      "hrid": "/items/crimson_buckler"
    },
    {
      "name": "Rainbow Buckler",
      "price": 299921,
      "hrid": "/items/rainbow_buckler"
    },
    {
      "name": "Holy Buckler",
      "price": 546104,
      "hrid": "/items/holy_buckler"
    },
    {
      "name": "Cheese Helmet",
      "price": 5148,
      "hrid": "/items/cheese_helmet"
    },
    {
      "name": "Verdant Helmet",
      "price": 15200,
      "hrid": "/items/verdant_helmet"
    },
    {
      "name": "Azure Helmet",
      "price": 35579,
      "hrid": "/items/azure_helmet"
    },
    {
      "name": "Burble Helmet",
      "price": 74766,
      "hrid": "/items/burble_helmet"
    },
    {
      "name": "Crimson Helmet",
      "price": 132099,
      "hrid": "/items/crimson_helmet"
    },
    {
      "name": "Rainbow Helmet",
      "price": 252368,
      "hrid": "/items/rainbow_helmet"
    },
    {
      "name": "Holy Helmet",
      "price": 459704,
      "hrid": "/items/holy_helmet"
    },
    {
      "name": "Cheese Plate Body",
      "price": 8019,
      "hrid": "/items/cheese_plate_body"
    },
    {
      "name": "Verdant Plate Body",
      "price": 23700,
      "hrid": "/items/verdant_plate_body"
    },
    {
      "name": "Azure Plate Body",
      "price": 55667,
      "hrid": "/items/azure_plate_body"
    },
    {
      "name": "Burble Plate Body",
      "price": 117203,
      "hrid": "/items/burble_plate_body"
    },
    {
      "name": "Crimson Plate Body",
      "price": 206835,
      "hrid": "/items/crimson_plate_body"
    },
    {
      "name": "Rainbow Plate Body",
      "price": 395288,
      "hrid": "/items/rainbow_plate_body"
    },
    {
      "name": "Holy Plate Body",
      "price": 719445,
      "hrid": "/items/holy_plate_body"
    },
    {
      "name": "Cheese Plate Legs",
      "price": 7062,
      "hrid": "/items/cheese_plate_legs"
    },
    {
      "name": "Verdant Plate Legs",
      "price": 20867,
      "hrid": "/items/verdant_plate_legs"
    },
    {
      "name": "Azure Plate Legs",
      "price": 48971,
      "hrid": "/items/azure_plate_legs"
    },
    {
      "name": "Burble Plate Legs",
      "price": 103057,
      "hrid": "/items/burble_plate_legs"
    },
    {
      "name": "Crimson Plate Legs",
      "price": 181923,
      "hrid": "/items/crimson_plate_legs"
    },
    {
      "name": "Rainbow Plate Legs",
      "price": 347647,
      "hrid": "/items/rainbow_plate_legs"
    },
    {
      "name": "Holy Plate Legs",
      "price": 632863,
      "hrid": "/items/holy_plate_legs"
    },
    {
      "name": "Cheese Gauntlets",
      "price": 4185,
      "hrid": "/items/cheese_gauntlets"
    },
    {
      "name": "Verdant Gauntlets",
      "price": 12347,
      "hrid": "/items/verdant_gauntlets"
    },
    {
      "name": "Azure Gauntlets",
      "price": 28843,
      "hrid": "/items/azure_gauntlets"
    },
    {
      "name": "Burble Gauntlets",
      "price": 60539,
      "hrid": "/items/burble_gauntlets"
    },
    {
      "name": "Crimson Gauntlets",
      "price": 107027,
      "hrid": "/items/crimson_gauntlets"
    },
    {
      "name": "Rainbow Gauntlets",
      "price": 204402,
      "hrid": "/items/rainbow_gauntlets"
    },
    {
      "name": "Holy Gauntlets",
      "price": 372448,
      "hrid": "/items/holy_gauntlets"
    },
    {
      "name": "Cheese Boots",
      "price": 4185,
      "hrid": "/items/cheese_boots"
    },
    {
      "name": "Verdant Boots",
      "price": 12344,
      "hrid": "/items/verdant_boots"
    },
    {
      "name": "Azure Boots",
      "price": 28835,
      "hrid": "/items/azure_boots"
    },
    {
      "name": "Burble Boots",
      "price": 60521,
      "hrid": "/items/burble_boots"
    },
    {
      "name": "Crimson Boots",
      "price": 106989,
      "hrid": "/items/crimson_boots"
    },
    {
      "name": "Rainbow Boots",
      "price": 204323,
      "hrid": "/items/rainbow_boots"
    },
    {
      "name": "Holy Boots",
      "price": 372285,
      "hrid": "/items/holy_boots"
    },
    {
      "name": "Rough Hood",
      "price": 5516,
      "hrid": "/items/rough_hood"
    },
    {
      "name": "Reptile Hood",
      "price": 17169,
      "hrid": "/items/reptile_hood"
    },
    {
      "name": "Gobo Hood",
      "price": 46494,
      "hrid": "/items/gobo_hood"
    },
    {
      "name": "Beast Hood",
      "price": 115313,
      "hrid": "/items/beast_hood"
    },
    {
      "name": "Umbral Hood",
      "price": 291590,
      "hrid": "/items/umbral_hood"
    },
    {
      "name": "Cotton Hat",
      "price": 5148,
      "hrid": "/items/cotton_hat"
    },
    {
      "name": "Linen Hat",
      "price": 20108,
      "hrid": "/items/linen_hat"
    },
    {
      "name": "Bamboo Hat",
      "price": 29987,
      "hrid": "/items/bamboo_hat"
    },
    {
      "name": "Silk Hat",
      "price": 142887,
      "hrid": "/items/silk_hat"
    },
    {
      "name": "Radiant Hat",
      "price": 385286,
      "hrid": "/items/radiant_hat"
    },
    {
      "name": "Rough Tunic",
      "price": 8612,
      "hrid": "/items/rough_tunic"
    },
    {
      "name": "Reptile Tunic",
      "price": 26687,
      "hrid": "/items/reptile_tunic"
    },
    {
      "name": "Gobo Tunic",
      "price": 72288,
      "hrid": "/items/gobo_tunic"
    },
    {
      "name": "Beast Tunic",
      "price": 179330,
      "hrid": "/items/beast_tunic"
    },
    {
      "name": "Umbral Tunic",
      "price": 455254,
      "hrid": "/items/umbral_tunic"
    },
    {
      "name": "Cotton Robe Top",
      "price": 8024,
      "hrid": "/items/cotton_robe_top"
    },
    {
      "name": "Linen Robe Top",
      "price": 31389,
      "hrid": "/items/linen_robe_top"
    },
    {
      "name": "Bamboo Robe Top",
      "price": 45876,
      "hrid": "/items/bamboo_robe_top"
    },
    {
      "name": "Silk Robe Top",
      "price": 223448,
      "hrid": "/items/silk_robe_top"
    },
    {
      "name": "Radiant Robe Top",
      "price": 605168,
      "hrid": "/items/radiant_robe_top"
    },
    {
      "name": "Rough Chaps",
      "price": 7578,
      "hrid": "/items/rough_chaps"
    },
    {
      "name": "Reptile Chaps",
      "price": 23507,
      "hrid": "/items/reptile_chaps"
    },
    {
      "name": "Gobo Chaps",
      "price": 63670,
      "hrid": "/items/gobo_chaps"
    },
    {
      "name": "Beast Chaps",
      "price": 157935,
      "hrid": "/items/beast_chaps"
    },
    {
      "name": "Umbral Chaps",
      "price": 400561,
      "hrid": "/items/umbral_chaps"
    },
    {
      "name": "Cotton Robe Bottoms",
      "price": 7064,
      "hrid": "/items/cotton_robe_bottoms"
    },
    {
      "name": "Linen Robe Bottoms",
      "price": 27622,
      "hrid": "/items/linen_robe_bottoms"
    },
    {
      "name": "Bamboo Robe Bottoms",
      "price": 40559,
      "hrid": "/items/bamboo_robe_bottoms"
    },
    {
      "name": "Silk Robe Bottoms",
      "price": 196538,
      "hrid": "/items/silk_robe_bottoms"
    },
    {
      "name": "Radiant Robe Bottoms",
      "price": 531736,
      "hrid": "/items/radiant_robe_bottoms"
    },
    {
      "name": "Rough Bracers",
      "price": 4482,
      "hrid": "/items/rough_bracers"
    },
    {
      "name": "Reptile Bracers",
      "price": 13991,
      "hrid": "/items/reptile_bracers"
    },
    {
      "name": "Gobo Bracers",
      "price": 37879,
      "hrid": "/items/gobo_bracers"
    },
    {
      "name": "Beast Bracers",
      "price": 93929,
      "hrid": "/items/beast_bracers"
    },
    {
      "name": "Umbral Bracers",
      "price": 236926,
      "hrid": "/items/umbral_bracers"
    },
    {
      "name": "Cotton Gloves",
      "price": 4188,
      "hrid": "/items/cotton_gloves"
    },
    {
      "name": "Linen Gloves",
      "price": 16342,
      "hrid": "/items/linen_gloves"
    },
    {
      "name": "Bamboo Gloves",
      "price": 24673,
      "hrid": "/items/bamboo_gloves"
    },
    {
      "name": "Silk Gloves",
      "price": 115988,
      "hrid": "/items/silk_gloves"
    },
    {
      "name": "Radiant Gloves",
      "price": 311883,
      "hrid": "/items/radiant_gloves"
    },
    {
      "name": "Rough Boots",
      "price": 4479,
      "hrid": "/items/rough_boots"
    },
    {
      "name": "Reptile Boots",
      "price": 13974,
      "hrid": "/items/reptile_boots"
    },
    {
      "name": "Gobo Boots",
      "price": 37827,
      "hrid": "/items/gobo_boots"
    },
    {
      "name": "Beast Boots",
      "price": 93784,
      "hrid": "/items/beast_boots"
    },
    {
      "name": "Umbral Boots",
      "price": 236572,
      "hrid": "/items/umbral_boots"
    },
    {
      "name": "Cotton Boots",
      "price": 4185,
      "hrid": "/items/cotton_boots"
    },
    {
      "name": "Linen Boots",
      "price": 16325,
      "hrid": "/items/linen_boots"
    },
    {
      "name": "Bamboo Boots",
      "price": 24621,
      "hrid": "/items/bamboo_boots"
    },
    {
      "name": "Silk Boots",
      "price": 115843,
      "hrid": "/items/silk_boots"
    },
    {
      "name": "Radiant Boots",
      "price": 311529,
      "hrid": "/items/radiant_boots"
    },
    {
      "name": "Wooden Crossbow",
      "price": 5467,
      "hrid": "/items/wooden_crossbow"
    },
    {
      "name": "Birch Crossbow",
      "price": 22993,
      "hrid": "/items/birch_crossbow"
    },
    {
      "name": "Cedar Crossbow",
      "price": 58770,
      "hrid": "/items/cedar_crossbow"
    },
    {
      "name": "Purpleheart Crossbow",
      "price": 132609,
      "hrid": "/items/purpleheart_crossbow"
    },
    {
      "name": "Ginkgo Crossbow",
      "price": 247679,
      "hrid": "/items/ginkgo_crossbow"
    },
    {
      "name": "Redwood Crossbow",
      "price": 447687,
      "hrid": "/items/redwood_crossbow"
    },
    {
      "name": "Arcane Crossbow",
      "price": 817321,
      "hrid": "/items/arcane_crossbow"
    },
    {
      "name": "Wooden Water Staff",
      "price": 5467,
      "hrid": "/items/wooden_water_staff"
    },
    {
      "name": "Birch Water Staff",
      "price": 22993,
      "hrid": "/items/birch_water_staff"
    },
    {
      "name": "Cedar Water Staff",
      "price": 58770,
      "hrid": "/items/cedar_water_staff"
    },
    {
      "name": "Purpleheart Water Staff",
      "price": 132609,
      "hrid": "/items/purpleheart_water_staff"
    },
    {
      "name": "Ginkgo Water Staff",
      "price": 247679,
      "hrid": "/items/ginkgo_water_staff"
    },
    {
      "name": "Redwood Water Staff",
      "price": 447687,
      "hrid": "/items/redwood_water_staff"
    },
    {
      "name": "Arcane Water Staff",
      "price": 817321,
      "hrid": "/items/arcane_water_staff"
    },
    {
      "name": "Wooden Nature Staff",
      "price": 5470,
      "hrid": "/items/wooden_nature_staff"
    },
    {
      "name": "Birch Nature Staff",
      "price": 23006,
      "hrid": "/items/birch_nature_staff"
    },
    {
      "name": "Cedar Nature Staff",
      "price": 58797,
      "hrid": "/items/cedar_nature_staff"
    },
    {
      "name": "Purpleheart Nature Staff",
      "price": 132667,
      "hrid": "/items/purpleheart_nature_staff"
    },
    {
      "name": "Ginkgo Nature Staff",
      "price": 247797,
      "hrid": "/items/ginkgo_nature_staff"
    },
    {
      "name": "Redwood Nature Staff",
      "price": 447928,
      "hrid": "/items/redwood_nature_staff"
    },
    {
      "name": "Arcane Nature Staff",
      "price": 817821,
      "hrid": "/items/arcane_nature_staff"
    },
    {
      "name": "Wooden Fire Staff",
      "price": 5475,
      "hrid": "/items/wooden_fire_staff"
    },
    {
      "name": "Birch Fire Staff",
      "price": 23020,
      "hrid": "/items/birch_fire_staff"
    },
    {
      "name": "Cedar Fire Staff",
      "price": 58828,
      "hrid": "/items/cedar_fire_staff"
    },
    {
      "name": "Purpleheart Fire Staff",
      "price": 132729,
      "hrid": "/items/purpleheart_fire_staff"
    },
    {
      "name": "Ginkgo Fire Staff",
      "price": 247920,
      "hrid": "/items/ginkgo_fire_staff"
    },
    {
      "name": "Redwood Fire Staff",
      "price": 448179,
      "hrid": "/items/redwood_fire_staff"
    },
    {
      "name": "Arcane Fire Staff",
      "price": 818341,
      "hrid": "/items/arcane_fire_staff"
    },
    {
      "name": "Wooden Bow",
      "price": 5473,
      "hrid": "/items/wooden_bow"
    },
    {
      "name": "Birch Bow",
      "price": 28636,
      "hrid": "/items/birch_bow"
    },
    {
      "name": "Cedar Bow",
      "price": 76010,
      "hrid": "/items/cedar_bow"
    },
    {
      "name": "Purpleheart Bow",
      "price": 173869,
      "hrid": "/items/purpleheart_bow"
    },
    {
      "name": "Ginkgo Bow",
      "price": 326233,
      "hrid": "/items/ginkgo_bow"
    },
    {
      "name": "Redwood Bow",
      "price": 590918,
      "hrid": "/items/redwood_bow"
    },
    {
      "name": "Arcane Bow",
      "price": 1080010,
      "hrid": "/items/arcane_bow"
    },
    {
      "name": "Wooden Shield",
      "price": 4554,
      "hrid": "/items/wooden_shield"
    },
    {
      "name": "Birch Shield",
      "price": 16466,
      "hrid": "/items/birch_shield"
    },
    {
      "name": "Cedar Shield",
      "price": 40681,
      "hrid": "/items/cedar_shield"
    },
    {
      "name": "Purpleheart Shield",
      "price": 90571,
      "hrid": "/items/purpleheart_shield"
    },
    {
      "name": "Ginkgo Shield",
      "price": 168487,
      "hrid": "/items/ginkgo_shield"
    },
    {
      "name": "Redwood Shield",
      "price": 304107,
      "hrid": "/items/redwood_shield"
    },
    {
      "name": "Arcane Shield",
      "price": 554892,
      "hrid": "/items/arcane_shield"
    }
  ],
  "time": 1756897961.386
}